{
"meta":{"test_sets":[],"test_metrics":[],"learn_metrics":[{"best_value":"Min","name":"Logloss"}],"launch_mode":"Train","parameters":"","iteration_count":1000,"learn_sets":["learn"],"name":"experiment"},
"iterations":[
{"learn":[0.6880155171],"iteration":0,"passed_time":0.01638789685,"remaining_time":16.37150896},
{"learn":[0.6832729184],"iteration":1,"passed_time":0.03265038113,"remaining_time":16.29254019},
{"learn":[0.677989221],"iteration":2,"passed_time":0.04854537544,"remaining_time":16.13324644},
{"learn":[0.6730816211],"iteration":3,"passed_time":0.06393838655,"remaining_time":15.92065825},
{"learn":[0.6677521762],"iteration":4,"passed_time":0.07903152552,"remaining_time":15.72727358},
{"learn":[0.6632293982],"iteration":5,"passed_time":0.09489606265,"remaining_time":15.72111438},
{"learn":[0.6590762121],"iteration":6,"passed_time":0.1110760369,"remaining_time":15.75692924},
{"learn":[0.652886988],"iteration":7,"passed_time":0.1310856131,"remaining_time":16.25461603},
{"learn":[0.6476455645],"iteration":8,"passed_time":0.1637251758,"remaining_time":18.02796102},
{"learn":[0.6428613866],"iteration":9,"passed_time":0.1833968826,"remaining_time":18.15629138},
{"learn":[0.6392827913],"iteration":10,"passed_time":0.2011158857,"remaining_time":18.08214645},
{"learn":[0.6339353008],"iteration":11,"passed_time":0.2181147206,"remaining_time":17.95811199},
{"learn":[0.6277403822],"iteration":12,"passed_time":0.2323348691,"remaining_time":17.63957814},
{"learn":[0.6254466997],"iteration":13,"passed_time":0.2371003416,"remaining_time":16.69863834},
{"learn":[0.6200281236],"iteration":14,"passed_time":0.249366236,"remaining_time":16.3750495},
{"learn":[0.614938853],"iteration":15,"passed_time":0.2610836574,"remaining_time":16.05664493},
{"learn":[0.6128691703],"iteration":16,"passed_time":0.2652155979,"remaining_time":15.33570192},
{"learn":[0.6079489047],"iteration":17,"passed_time":0.2780370514,"remaining_time":15.16846581},
{"learn":[0.6032025519],"iteration":18,"passed_time":0.2899713095,"remaining_time":14.97167656},
{"learn":[0.5985527035],"iteration":19,"passed_time":0.3017749727,"remaining_time":14.78697366},
{"learn":[0.5951967362],"iteration":20,"passed_time":0.3156215059,"remaining_time":14.71397401},
{"learn":[0.5902409907],"iteration":21,"passed_time":0.3277199205,"remaining_time":14.5686401},
{"learn":[0.5855788321],"iteration":22,"passed_time":0.3392385302,"remaining_time":14.41026278},
{"learn":[0.5837546693],"iteration":23,"passed_time":0.3438750639,"remaining_time":13.9842526},
{"learn":[0.5794732049],"iteration":24,"passed_time":0.3550490219,"remaining_time":13.84691185},
{"learn":[0.5754315345],"iteration":25,"passed_time":0.3669629114,"remaining_time":13.74699522},
{"learn":[0.5705357234],"iteration":26,"passed_time":0.3796356554,"remaining_time":13.68094418},
{"learn":[0.5657188357],"iteration":27,"passed_time":0.3907964825,"remaining_time":13.56622075},
{"learn":[0.5612486707],"iteration":28,"passed_time":0.4026160028,"remaining_time":13.48069444},
{"learn":[0.5574116637],"iteration":29,"passed_time":0.4152205953,"remaining_time":13.42546591},
{"learn":[0.5537308516],"iteration":30,"passed_time":0.4280013639,"remaining_time":13.37849425},
{"learn":[0.5502619309],"iteration":31,"passed_time":0.4402266689,"remaining_time":13.31685673},
{"learn":[0.5468807022],"iteration":32,"passed_time":0.4548990023,"remaining_time":13.32991925},
{"learn":[0.5448857262],"iteration":33,"passed_time":0.4621110419,"remaining_time":13.12939019},
{"learn":[0.5411321879],"iteration":34,"passed_time":0.4738668503,"remaining_time":13.06518602},
{"learn":[0.5370039391],"iteration":35,"passed_time":0.485407968,"remaining_time":12.9981467},
{"learn":[0.533108435],"iteration":36,"passed_time":0.4971234166,"remaining_time":12.9386446},
{"learn":[0.5300284079],"iteration":37,"passed_time":0.5097418046,"remaining_time":12.90451621},
{"learn":[0.5285464005],"iteration":38,"passed_time":0.5144938204,"remaining_time":12.67765542},
{"learn":[0.5259212547],"iteration":39,"passed_time":0.5277859441,"remaining_time":12.66686266},
{"learn":[0.5229635274],"iteration":40,"passed_time":0.5392966135,"remaining_time":12.61427932},
{"learn":[0.5203418827],"iteration":41,"passed_time":0.5502052942,"remaining_time":12.54992076},
{"learn":[0.5180060323],"iteration":42,"passed_time":0.5614744527,"remaining_time":12.49607096},
{"learn":[0.5144996415],"iteration":43,"passed_time":0.5739278331,"remaining_time":12.46988656},
{"learn":[0.5114642732],"iteration":44,"passed_time":0.5849032821,"remaining_time":12.41294743},
{"learn":[0.5083945597],"iteration":45,"passed_time":0.597937538,"remaining_time":12.40070459},
{"learn":[0.5058002654],"iteration":46,"passed_time":0.6107686346,"remaining_time":12.3843087},
{"learn":[0.5028705724],"iteration":47,"passed_time":0.6238376977,"remaining_time":12.37278101},
{"learn":[0.500161751],"iteration":48,"passed_time":0.6361446877,"remaining_time":12.34639996},
{"learn":[0.496997231],"iteration":49,"passed_time":0.6476653372,"remaining_time":12.30564141},
{"learn":[0.4936229854],"iteration":50,"passed_time":0.6601306687,"remaining_time":12.28360793},
{"learn":[0.4913236425],"iteration":51,"passed_time":0.6721985625,"remaining_time":12.25469687},
{"learn":[0.489116166],"iteration":52,"passed_time":0.6836545036,"remaining_time":12.21548707},
{"learn":[0.4880453778],"iteration":53,"passed_time":0.6882630574,"remaining_time":12.05734912},
{"learn":[0.4852228622],"iteration":54,"passed_time":0.6994552433,"remaining_time":12.01791282},
{"learn":[0.4825109541],"iteration":55,"passed_time":0.7134029886,"remaining_time":12.02593609},
{"learn":[0.4789347234],"iteration":56,"passed_time":0.7265965005,"remaining_time":12.02071053},
{"learn":[0.4764119077],"iteration":57,"passed_time":0.7395443382,"remaining_time":12.01122011},
{"learn":[0.4738362923],"iteration":58,"passed_time":0.7529262385,"remaining_time":12.00853543},
{"learn":[0.4711292614],"iteration":59,"passed_time":0.7648262666,"remaining_time":11.98227818},
{"learn":[0.4691668434],"iteration":60,"passed_time":0.7735745125,"remaining_time":11.90797487},
{"learn":[0.4658449819],"iteration":61,"passed_time":0.7851464199,"remaining_time":11.87850551},
{"learn":[0.4632451107],"iteration":62,"passed_time":0.7967623231,"remaining_time":11.85025868},
{"learn":[0.4615154558],"iteration":63,"passed_time":0.8089270593,"remaining_time":11.83055824},
{"learn":[0.4605769696],"iteration":64,"passed_time":0.8135638783,"remaining_time":11.70280348},
{"learn":[0.4575983896],"iteration":65,"passed_time":0.8255695146,"remaining_time":11.68305949},
{"learn":[0.4554228107],"iteration":66,"passed_time":0.8385160791,"remaining_time":11.67664928},
{"learn":[0.4523190981],"iteration":67,"passed_time":0.8505030617,"remaining_time":11.6568949},
{"learn":[0.4491736041],"iteration":68,"passed_time":0.8617271238,"remaining_time":11.62707177},
{"learn":[0.4462620957],"iteration":69,"passed_time":0.8737729031,"remaining_time":11.60869714},
{"learn":[0.4439865056],"iteration":70,"passed_time":0.8862689135,"remaining_time":11.59639184},
{"learn":[0.4415964827],"iteration":71,"passed_time":0.8978162347,"remaining_time":11.57185369},
{"learn":[0.4387810404],"iteration":72,"passed_time":0.9101086241,"remaining_time":11.5571328},
{"learn":[0.4363876874],"iteration":73,"passed_time":0.9224362962,"remaining_time":11.54291906},
{"learn":[0.4342120156],"iteration":74,"passed_time":0.9340594456,"remaining_time":11.5200665},
{"learn":[0.4324970135],"iteration":75,"passed_time":0.947151241,"remaining_time":11.51536509},
{"learn":[0.43021904],"iteration":76,"passed_time":0.960086521,"remaining_time":11.5085696},
{"learn":[0.4290972572],"iteration":77,"passed_time":0.9697617123,"remaining_time":11.46308075},
{"learn":[0.4269845275],"iteration":78,"passed_time":0.9817062795,"remaining_time":11.44495549},
{"learn":[0.4244639773],"iteration":79,"passed_time":0.9942891707,"remaining_time":11.43432546},
{"learn":[0.4226365598],"iteration":80,"passed_time":1.006457071,"remaining_time":11.41893887},
{"learn":[0.4210403963],"iteration":81,"passed_time":1.018614742,"remaining_time":11.40351626},
{"learn":[0.4185836043],"iteration":82,"passed_time":1.030469212,"remaining_time":11.3848225},
{"learn":[0.4174816146],"iteration":83,"passed_time":1.037586577,"remaining_time":11.31463457},
{"learn":[0.4153309624],"iteration":84,"passed_time":1.04974238,"remaining_time":11.30016797},
{"learn":[0.4133290165],"iteration":85,"passed_time":1.062187453,"remaining_time":11.28882944},
{"learn":[0.4112823078],"iteration":86,"passed_time":1.074256397,"remaining_time":11.27351828},
{"learn":[0.4094028999],"iteration":87,"passed_time":1.086248512,"remaining_time":11.25748458},
{"learn":[0.4080805033],"iteration":88,"passed_time":1.097190949,"remaining_time":11.23079724},
{"learn":[0.4064071225],"iteration":89,"passed_time":1.109203068,"remaining_time":11.21527546},
{"learn":[0.4045656531],"iteration":90,"passed_time":1.122873732,"remaining_time":11.21639805},
{"learn":[0.4028773107],"iteration":91,"passed_time":1.135689088,"remaining_time":11.20875752},
{"learn":[0.4015779435],"iteration":92,"passed_time":1.149532176,"remaining_time":11.21102886},
{"learn":[0.4001044114],"iteration":93,"passed_time":1.162709979,"remaining_time":11.20654512},
{"learn":[0.3982261336],"iteration":94,"passed_time":1.176592262,"remaining_time":11.20858945},
{"learn":[0.3959850345],"iteration":95,"passed_time":1.189160924,"remaining_time":11.19793203},
{"learn":[0.3946261929],"iteration":96,"passed_time":1.202311486,"remaining_time":11.19265228},
{"learn":[0.3929306634],"iteration":97,"passed_time":1.216507358,"remaining_time":11.19683303},
{"learn":[0.3907608937],"iteration":98,"passed_time":1.22810979,"remaining_time":11.17703961},
{"learn":[0.388849557],"iteration":99,"passed_time":1.241860185,"remaining_time":11.17674167},
{"learn":[0.3871063865],"iteration":100,"passed_time":1.263062619,"remaining_time":11.24250787},
{"learn":[0.3855229525],"iteration":101,"passed_time":1.277400068,"remaining_time":11.24613001},
{"learn":[0.38377484],"iteration":102,"passed_time":1.299229576,"remaining_time":11.3146498},
{"learn":[0.381759392],"iteration":103,"passed_time":1.313186987,"remaining_time":11.31361096},
{"learn":[0.380360988],"iteration":104,"passed_time":1.327119447,"remaining_time":11.31211338},
{"learn":[0.3786074825],"iteration":105,"passed_time":1.338101394,"remaining_time":11.28549666},
{"learn":[0.3770775811],"iteration":106,"passed_time":1.351219899,"remaining_time":11.27700346},
{"learn":[0.3753705514],"iteration":107,"passed_time":1.363332642,"remaining_time":11.26011774},
{"learn":[0.3737503644],"iteration":108,"passed_time":1.376163692,"remaining_time":11.24919128},
{"learn":[0.3723048307],"iteration":109,"passed_time":1.389556342,"remaining_time":11.24277404},
{"learn":[0.3706392076],"iteration":110,"passed_time":1.403632002,"remaining_time":11.24170135},
{"learn":[0.3690414766],"iteration":111,"passed_time":1.417892069,"remaining_time":11.24185855},
{"learn":[0.3672233437],"iteration":112,"passed_time":1.42984929,"remaining_time":11.22368425},
{"learn":[0.3655607825],"iteration":113,"passed_time":1.44336772,"remaining_time":11.21775263},
{"learn":[0.3643733743],"iteration":114,"passed_time":1.457392408,"remaining_time":11.21558505},
{"learn":[0.3631749274],"iteration":115,"passed_time":1.472059644,"remaining_time":11.2181097},
{"learn":[0.3628203298],"iteration":116,"passed_time":1.477091412,"remaining_time":11.14762151},
{"learn":[0.3610876714],"iteration":117,"passed_time":1.49046525,"remaining_time":11.14059619},
{"learn":[0.3592842157],"iteration":118,"passed_time":1.504669015,"remaining_time":11.13960842},
{"learn":[0.3585218053],"iteration":119,"passed_time":1.51525551,"remaining_time":11.11187374},
{"learn":[0.3572622093],"iteration":120,"passed_time":1.527480568,"remaining_time":11.09632578},
{"learn":[0.3560272788],"iteration":121,"passed_time":1.54079806,"remaining_time":11.08869424},
{"learn":[0.3548266393],"iteration":122,"passed_time":1.554337188,"remaining_time":11.08255052},
{"learn":[0.3536955823],"iteration":123,"passed_time":1.568237715,"remaining_time":11.07884063},
{"learn":[0.3528818802],"iteration":124,"passed_time":1.581894736,"remaining_time":11.07326315},
{"learn":[0.3511042138],"iteration":125,"passed_time":1.59506479,"remaining_time":11.06417958},
{"learn":[0.3496034051],"iteration":126,"passed_time":1.608732776,"remaining_time":11.05845444},
{"learn":[0.3485181972],"iteration":127,"passed_time":1.621841559,"remaining_time":11.04879562},
{"learn":[0.3469703959],"iteration":128,"passed_time":1.634978651,"remaining_time":11.03927445},
{"learn":[0.3458888989],"iteration":129,"passed_time":1.648328213,"remaining_time":11.03111958},
{"learn":[0.3445614849],"iteration":130,"passed_time":1.662360721,"remaining_time":11.02741577},
{"learn":[0.343214491],"iteration":131,"passed_time":1.676550064,"remaining_time":11.02458678},
{"learn":[0.3417818817],"iteration":132,"passed_time":1.690329772,"remaining_time":11.01891664},
{"learn":[0.3408432124],"iteration":133,"passed_time":1.7073374,"remaining_time":11.03398648},
{"learn":[0.3394231525],"iteration":134,"passed_time":1.720934674,"remaining_time":11.02672958},
{"learn":[0.3381954772],"iteration":135,"passed_time":1.733963254,"remaining_time":11.01576655},
{"learn":[0.3370399926],"iteration":136,"passed_time":1.747536916,"remaining_time":11.00820699},
{"learn":[0.3360311169],"iteration":137,"passed_time":1.760991946,"remaining_time":10.99981925},
{"learn":[0.3344618225],"iteration":138,"passed_time":1.776355187,"remaining_time":11.00317853},
{"learn":[0.3332980079],"iteration":139,"passed_time":1.789528385,"remaining_time":10.99281722},
{"learn":[0.3318993982],"iteration":140,"passed_time":1.803147853,"remaining_time":10.98513479},
{"learn":[0.3305086054],"iteration":141,"passed_time":1.816253243,"remaining_time":10.97426255},
{"learn":[0.3296840612],"iteration":142,"passed_time":1.828012018,"remaining_time":10.9552888},
{"learn":[0.3287030071],"iteration":143,"passed_time":1.839603242,"remaining_time":10.93541927},
{"learn":[0.3279363894],"iteration":144,"passed_time":1.851238234,"remaining_time":10.915922},
{"learn":[0.3267464766],"iteration":145,"passed_time":1.864369955,"remaining_time":10.90528727},
{"learn":[0.3257507556],"iteration":146,"passed_time":1.87728734,"remaining_time":10.89337484},
{"learn":[0.324841701],"iteration":147,"passed_time":1.890032121,"remaining_time":10.88045518},
{"learn":[0.3239701355],"iteration":148,"passed_time":1.902088469,"remaining_time":10.86360595},
{"learn":[0.3229327726],"iteration":149,"passed_time":1.913938949,"remaining_time":10.84565404},
{"learn":[0.3216821164],"iteration":150,"passed_time":1.926213622,"remaining_time":10.83016798},
{"learn":[0.3205974246],"iteration":151,"passed_time":1.94120554,"remaining_time":10.82988354},
{"learn":[0.3192690295],"iteration":152,"passed_time":1.956318703,"remaining_time":10.83007805},
{"learn":[0.3190215515],"iteration":153,"passed_time":1.962482698,"remaining_time":10.78091145},
{"learn":[0.3178134167],"iteration":154,"passed_time":1.974642317,"remaining_time":10.76498554},
{"learn":[0.3167879627],"iteration":155,"passed_time":1.986450005,"remaining_time":10.74720387},
{"learn":[0.3155925121],"iteration":156,"passed_time":1.998614637,"remaining_time":10.7314149},
{"learn":[0.3144973356],"iteration":157,"passed_time":2.010563197,"remaining_time":10.71452033},
{"learn":[0.3133590533],"iteration":158,"passed_time":2.02217122,"remaining_time":10.69588677},
{"learn":[0.3123705809],"iteration":159,"passed_time":2.034134569,"remaining_time":10.67920649},
{"learn":[0.3112573343],"iteration":160,"passed_time":2.046594263,"remaining_time":10.66517135},
{"learn":[0.3102625731],"iteration":161,"passed_time":2.059440209,"remaining_time":10.65315368},
{"learn":[0.3097650193],"iteration":162,"passed_time":2.071490959,"remaining_time":10.63704253},
{"learn":[0.3087524988],"iteration":163,"passed_time":2.084653595,"remaining_time":10.62664881},
{"learn":[0.3081587118],"iteration":164,"passed_time":2.096662335,"remaining_time":10.61038212},
{"learn":[0.3072718464],"iteration":165,"passed_time":2.108170634,"remaining_time":10.59165246},
{"learn":[0.3063399653],"iteration":166,"passed_time":2.119530212,"remaining_time":10.57226746},
{"learn":[0.3052257329],"iteration":167,"passed_time":2.131377134,"remaining_time":10.55539152},
{"learn":[0.3037235379],"iteration":168,"passed_time":2.142886857,"remaining_time":10.53691703},
{"learn":[0.3030748063],"iteration":169,"passed_time":2.15471659,"remaining_time":10.52008688},
{"learn":[0.3019263232],"iteration":170,"passed_time":2.168227277,"remaining_time":10.5114644},
{"learn":[0.3011406166],"iteration":171,"passed_time":2.181919258,"remaining_time":10.50365782},
{"learn":[0.3003988782],"iteration":172,"passed_time":2.195543006,"remaining_time":10.49545703},
{"learn":[0.299945189],"iteration":173,"passed_time":2.207836992,"remaining_time":10.48088135},
{"learn":[0.2992681009],"iteration":174,"passed_time":2.21935794,"remaining_time":10.46268743},
{"learn":[0.2983860072],"iteration":175,"passed_time":2.231373518,"remaining_time":10.44688511},
{"learn":[0.2971884418],"iteration":176,"passed_time":2.243470018,"remaining_time":10.43150183},
{"learn":[0.2967137862],"iteration":177,"passed_time":2.254771156,"remaining_time":10.41248253},
{"learn":[0.2957858437],"iteration":178,"passed_time":2.266900768,"remaining_time":10.39734933},
{"learn":[0.2948628278],"iteration":179,"passed_time":2.280475806,"remaining_time":10.38883423},
{"learn":[0.2937400206],"iteration":180,"passed_time":2.293837455,"remaining_time":10.37929766},
{"learn":[0.292803894],"iteration":181,"passed_time":2.306533314,"remaining_time":10.36672665},
{"learn":[0.292317731],"iteration":182,"passed_time":2.318714186,"remaining_time":10.35185514},
{"learn":[0.291305795],"iteration":183,"passed_time":2.330472279,"remaining_time":10.33513793},
{"learn":[0.2904873462],"iteration":184,"passed_time":2.341977278,"remaining_time":10.31735936},
{"learn":[0.2898204769],"iteration":185,"passed_time":2.352890189,"remaining_time":10.29705706},
{"learn":[0.2885857243],"iteration":186,"passed_time":2.365288126,"remaining_time":10.28331148},
{"learn":[0.2880504702],"iteration":187,"passed_time":2.37729153,"remaining_time":10.26787618},
{"learn":[0.2875420422],"iteration":188,"passed_time":2.386907201,"remaining_time":10.24223143},
{"learn":[0.2865876994],"iteration":189,"passed_time":2.4004626,"remaining_time":10.23355108},
{"learn":[0.2858674985],"iteration":190,"passed_time":2.41268399,"remaining_time":10.21916936},
{"learn":[0.2851819898],"iteration":191,"passed_time":2.424363059,"remaining_time":10.20252787},
{"learn":[0.2843921009],"iteration":192,"passed_time":2.436100805,"remaining_time":10.18618316},
{"learn":[0.2837020141],"iteration":193,"passed_time":2.448532262,"remaining_time":10.17276806},
{"learn":[0.2827972335],"iteration":194,"passed_time":2.461431257,"remaining_time":10.16129314},
{"learn":[0.2824153656],"iteration":195,"passed_time":2.469280946,"remaining_time":10.12909123},
{"learn":[0.2815494079],"iteration":196,"passed_time":2.479224643,"remaining_time":10.10567202},
{"learn":[0.2811556299],"iteration":197,"passed_time":2.49238155,"remaining_time":10.09540406},
{"learn":[0.2802098921],"iteration":198,"passed_time":2.504618259,"remaining_time":10.08140314},
{"learn":[0.2792953796],"iteration":199,"passed_time":2.516491412,"remaining_time":10.06596565},
{"learn":[0.2783880684],"iteration":200,"passed_time":2.528430263,"remaining_time":10.05082478},
{"learn":[0.2778024895],"iteration":201,"passed_time":2.540690136,"remaining_time":10.0369838},
{"learn":[0.2772389531],"iteration":202,"passed_time":2.552689906,"remaining_time":10.02213722},
{"learn":[0.2763981918],"iteration":203,"passed_time":2.564620011,"remaining_time":10.00704671},
{"learn":[0.2753317097],"iteration":204,"passed_time":2.577025125,"remaining_time":9.993829144},
{"learn":[0.274062973],"iteration":205,"passed_time":2.588886795,"remaining_time":9.978524832},
{"learn":[0.2734854637],"iteration":206,"passed_time":2.603113277,"remaining_time":9.972313184},
{"learn":[0.2728603188],"iteration":207,"passed_time":2.615659638,"remaining_time":9.959627084},
{"learn":[0.2722568001],"iteration":208,"passed_time":2.625953152,"remaining_time":9.938415998},
{"learn":[0.2716318739],"iteration":209,"passed_time":2.63829056,"remaining_time":9.92499782},
{"learn":[0.2706882854],"iteration":210,"passed_time":2.650118064,"remaining_time":9.909683188},
{"learn":[0.2701082246],"iteration":211,"passed_time":2.668594694,"remaining_time":9.919116128},
{"learn":[0.2696499556],"iteration":212,"passed_time":2.681034563,"remaining_time":9.905982166},
{"learn":[0.2690217949],"iteration":213,"passed_time":2.6944077,"remaining_time":9.896282487},
{"learn":[0.2681640746],"iteration":214,"passed_time":2.707179724,"remaining_time":9.884353877},
{"learn":[0.2671470689],"iteration":215,"passed_time":2.719026261,"remaining_time":9.86905828},
{"learn":[0.2668487694],"iteration":216,"passed_time":2.731330268,"remaining_time":9.855445162},
{"learn":[0.2658524514],"iteration":217,"passed_time":2.743527781,"remaining_time":9.841462039},
{"learn":[0.2650015743],"iteration":218,"passed_time":2.755923332,"remaining_time":9.828201473},
{"learn":[0.264274571],"iteration":219,"passed_time":2.767577319,"remaining_time":9.812319584},
{"learn":[0.2638071622],"iteration":220,"passed_time":2.77870905,"remaining_time":9.794635069},
{"learn":[0.2631044472],"iteration":221,"passed_time":2.791212472,"remaining_time":9.781816681},
{"learn":[0.2619312008],"iteration":222,"passed_time":2.803405219,"remaining_time":9.767918633},
{"learn":[0.2614931435],"iteration":223,"passed_time":2.816621718,"remaining_time":9.75758238},
{"learn":[0.2607595332],"iteration":224,"passed_time":2.828844537,"remaining_time":9.743797851},
{"learn":[0.2600152904],"iteration":225,"passed_time":2.841079682,"remaining_time":9.730069354},
{"learn":[0.2591997559],"iteration":226,"passed_time":2.852855924,"remaining_time":9.714791317},
{"learn":[0.2589017902],"iteration":227,"passed_time":2.862880351,"remaining_time":9.693612417},
{"learn":[0.2579662316],"iteration":228,"passed_time":2.874608771,"remaining_time":9.678267957},
{"learn":[0.2573043298],"iteration":229,"passed_time":2.88620054,"remaining_time":9.662497459},
{"learn":[0.2564494977],"iteration":230,"passed_time":2.898297503,"remaining_time":9.648444934},
{"learn":[0.2559727379],"iteration":231,"passed_time":2.911840015,"remaining_time":9.639194531},
{"learn":[0.2553217898],"iteration":232,"passed_time":2.923762525,"remaining_time":9.624574491},
{"learn":[0.2546013234],"iteration":233,"passed_time":2.935069878,"remaining_time":9.607963787},
{"learn":[0.2538503071],"iteration":234,"passed_time":2.946553292,"remaining_time":9.591971354},
{"learn":[0.253361904],"iteration":235,"passed_time":2.958725847,"remaining_time":9.57824808},
{"learn":[0.2523591267],"iteration":236,"passed_time":2.970443617,"remaining_time":9.563073756},
{"learn":[0.2518853731],"iteration":237,"passed_time":2.981908023,"remaining_time":9.547117283},
{"learn":[0.2512350094],"iteration":238,"passed_time":2.9938091,"remaining_time":9.532588809},
{"learn":[0.2507979694],"iteration":239,"passed_time":3.006145049,"remaining_time":9.519459321},
{"learn":[0.2501194284],"iteration":240,"passed_time":3.018000287,"remaining_time":9.504822482},
{"learn":[0.2497623216],"iteration":241,"passed_time":3.031251191,"remaining_time":9.494580176},
{"learn":[0.2492915636],"iteration":242,"passed_time":3.042651634,"remaining_time":9.478548506},
{"learn":[0.2486757936],"iteration":243,"passed_time":3.055600544,"remaining_time":9.467352504},
{"learn":[0.2481888008],"iteration":244,"passed_time":3.066535705,"remaining_time":9.449936559},
{"learn":[0.2474662244],"iteration":245,"passed_time":3.078219292,"remaining_time":9.434867261},
{"learn":[0.2470321634],"iteration":246,"passed_time":3.089880553,"remaining_time":9.419757312},
{"learn":[0.2464362322],"iteration":247,"passed_time":3.101272065,"remaining_time":9.403857229},
{"learn":[0.2458805079],"iteration":248,"passed_time":3.112834323,"remaining_time":9.388508341},
{"learn":[0.2453568345],"iteration":249,"passed_time":3.125857171,"remaining_time":9.377571514},
{"learn":[0.2449101731],"iteration":250,"passed_time":3.138108288,"remaining_time":9.36431517},
{"learn":[0.2444315797],"iteration":251,"passed_time":3.149559926,"remaining_time":9.348693747},
{"learn":[0.243938491],"iteration":252,"passed_time":3.161149693,"remaining_time":9.333513125},
{"learn":[0.2434598605],"iteration":253,"passed_time":3.172782995,"remaining_time":9.318488638},
{"learn":[0.2430486677],"iteration":254,"passed_time":3.184874617,"remaining_time":9.304829763},
{"learn":[0.2428807199],"iteration":255,"passed_time":3.196504728,"remaining_time":9.289841865},
{"learn":[0.2424866191],"iteration":256,"passed_time":3.20838263,"remaining_time":9.275596476},
{"learn":[0.2418123344],"iteration":257,"passed_time":3.221159074,"remaining_time":9.263953615},
{"learn":[0.2410744357],"iteration":258,"passed_time":3.233046664,"remaining_time":9.24975899},
{"learn":[0.2406869695],"iteration":259,"passed_time":3.244419868,"remaining_time":9.234118085},
{"learn":[0.2401083834],"iteration":260,"passed_time":3.256850059,"remaining_time":9.221502656},
{"learn":[0.239485995],"iteration":261,"passed_time":3.269013673,"remaining_time":9.20813775},
{"learn":[0.2391324354],"iteration":262,"passed_time":3.280366062,"remaining_time":9.192508699},
{"learn":[0.2386664363],"iteration":263,"passed_time":3.292835412,"remaining_time":9.180025998},
{"learn":[0.237910522],"iteration":264,"passed_time":3.306097516,"remaining_time":9.169742168},
{"learn":[0.2372555482],"iteration":265,"passed_time":3.318582653,"remaining_time":9.157291983},
{"learn":[0.2369974032],"iteration":266,"passed_time":3.330760133,"remaining_time":9.143996918},
{"learn":[0.2366507716],"iteration":267,"passed_time":3.343674019,"remaining_time":9.132721575},
{"learn":[0.2362567686],"iteration":268,"passed_time":3.355680253,"remaining_time":9.118967527},
{"learn":[0.2357660031],"iteration":269,"passed_time":3.367373514,"remaining_time":9.104380242},
{"learn":[0.2352992275],"iteration":270,"passed_time":3.3791886,"remaining_time":9.090142027},
{"learn":[0.2347339221],"iteration":271,"passed_time":3.391057417,"remaining_time":9.076065439},
{"learn":[0.2345180848],"iteration":272,"passed_time":3.404083549,"remaining_time":9.06508696},
{"learn":[0.2340022709],"iteration":273,"passed_time":3.416134158,"remaining_time":9.051508754},
{"learn":[0.2336280402],"iteration":274,"passed_time":3.428179597,"remaining_time":9.037928028},
{"learn":[0.2333065736],"iteration":275,"passed_time":3.441945326,"remaining_time":9.028871073},
{"learn":[0.2328015565],"iteration":276,"passed_time":3.454414579,"remaining_time":9.016396175},
{"learn":[0.2322388573],"iteration":277,"passed_time":3.46565832,"remaining_time":9.000738515},
{"learn":[0.2316333183],"iteration":278,"passed_time":3.477361638,"remaining_time":8.986300147},
{"learn":[0.2309768074],"iteration":279,"passed_time":3.490022439,"remaining_time":8.974343416},
{"learn":[0.2308116749],"iteration":280,"passed_time":3.502450907,"remaining_time":8.961787195},
{"learn":[0.2304416839],"iteration":281,"passed_time":3.513713225,"remaining_time":8.94626275},
{"learn":[0.2299847302],"iteration":282,"passed_time":3.525988977,"remaining_time":8.93333603},
{"learn":[0.2293872564],"iteration":283,"passed_time":3.538969187,"remaining_time":8.922189921},
{"learn":[0.2289679429],"iteration":284,"passed_time":3.550516294,"remaining_time":8.907435616},
{"learn":[0.2286975701],"iteration":285,"passed_time":3.562023357,"remaining_time":8.892603764},
{"learn":[0.2286073278],"iteration":286,"passed_time":3.569500669,"remaining_time":8.867783893},
{"learn":[0.2279286786],"iteration":287,"passed_time":3.580905555,"remaining_time":8.852794288},
{"learn":[0.2274067022],"iteration":288,"passed_time":3.592831305,"remaining_time":8.839110928},
{"learn":[0.2267937843],"iteration":289,"passed_time":3.604850794,"remaining_time":8.825669184},
{"learn":[0.2264078294],"iteration":290,"passed_time":3.617382951,"remaining_time":8.813486297},
{"learn":[0.2259267817],"iteration":291,"passed_time":3.629501519,"remaining_time":8.800298205},
{"learn":[0.2255581344],"iteration":292,"passed_time":3.642936925,"remaining_time":8.790294902},
{"learn":[0.2250916861],"iteration":293,"passed_time":3.657582578,"remaining_time":8.78317449},
{"learn":[0.2243399979],"iteration":294,"passed_time":3.670404081,"remaining_time":8.771643652},
{"learn":[0.2240898809],"iteration":295,"passed_time":3.682073813,"remaining_time":8.757364745},
{"learn":[0.2234358854],"iteration":296,"passed_time":3.695852102,"remaining_time":8.74809437},
{"learn":[0.2233664181],"iteration":297,"passed_time":3.705404231,"remaining_time":8.728838155},
{"learn":[0.2228400986],"iteration":298,"passed_time":3.713951821,"remaining_time":8.707291728},
{"learn":[0.2222765979],"iteration":299,"passed_time":3.72538799,"remaining_time":8.692571976},
{"learn":[0.2219261717],"iteration":300,"passed_time":3.737295161,"remaining_time":8.678967833},
{"learn":[0.2215292332],"iteration":301,"passed_time":3.750560098,"remaining_time":8.668513075},
{"learn":[0.2209891592],"iteration":302,"passed_time":3.762310721,"remaining_time":8.654556344},
{"learn":[0.2205920545],"iteration":303,"passed_time":3.774334772,"remaining_time":8.641240136},
{"learn":[0.2202048301],"iteration":304,"passed_time":3.786690908,"remaining_time":8.628689118},
{"learn":[0.2198029079],"iteration":305,"passed_time":3.798978927,"remaining_time":8.615984886},
{"learn":[0.2195076687],"iteration":306,"passed_time":3.810914988,"remaining_time":8.602488882},
{"learn":[0.2189967222],"iteration":307,"passed_time":3.823289252,"remaining_time":8.589987541},
{"learn":[0.2184543568],"iteration":308,"passed_time":3.835855522,"remaining_time":8.577916393},
{"learn":[0.2183787936],"iteration":309,"passed_time":3.844053399,"remaining_time":8.556118856},
{"learn":[0.2180438297],"iteration":310,"passed_time":3.855861606,"remaining_time":8.542407223},
{"learn":[0.2175443047],"iteration":311,"passed_time":3.869400106,"remaining_time":8.532523312},
{"learn":[0.2170986598],"iteration":312,"passed_time":3.881507751,"remaining_time":8.51947548},
{"learn":[0.2167516746],"iteration":313,"passed_time":3.893078611,"remaining_time":8.505260913},
{"learn":[0.2166421039],"iteration":314,"passed_time":3.901137159,"remaining_time":8.483425251},
{"learn":[0.216154161],"iteration":315,"passed_time":3.91345331,"remaining_time":8.470892607},
{"learn":[0.215649895],"iteration":316,"passed_time":3.925103867,"remaining_time":8.456927259},
{"learn":[0.2151327149],"iteration":317,"passed_time":3.937220812,"remaining_time":8.443976709},
{"learn":[0.2148280004],"iteration":318,"passed_time":3.950009135,"remaining_time":8.432464643},
{"learn":[0.2145269946],"iteration":319,"passed_time":3.962305817,"remaining_time":8.41989986},
{"learn":[0.2141893505],"iteration":320,"passed_time":3.975410616,"remaining_time":8.409046131},
{"learn":[0.2137728784],"iteration":321,"passed_time":3.988325015,"remaining_time":8.397777516},
{"learn":[0.2135952995],"iteration":322,"passed_time":3.99832034,"remaining_time":8.380380403},
{"learn":[0.2130442097],"iteration":323,"passed_time":4.009785962,"remaining_time":8.366096638},
{"learn":[0.2123883257],"iteration":324,"passed_time":4.021645317,"remaining_time":8.352647965},
{"learn":[0.2120271685],"iteration":325,"passed_time":4.034474953,"remaining_time":8.341215088},
{"learn":[0.2117456891],"iteration":326,"passed_time":4.046862023,"remaining_time":8.328862819},
{"learn":[0.2113163332],"iteration":327,"passed_time":4.058851758,"remaining_time":8.315696285},
{"learn":[0.2110679062],"iteration":328,"passed_time":4.073083167,"remaining_time":8.307108829},
{"learn":[0.2106085468],"iteration":329,"passed_time":4.08615763,"remaining_time":8.296138219},
{"learn":[0.210123831],"iteration":330,"passed_time":4.098719278,"remaining_time":8.28411842},
{"learn":[0.2096702975],"iteration":331,"passed_time":4.110378376,"remaining_time":8.270279382},
{"learn":[0.2092197531],"iteration":332,"passed_time":4.122141472,"remaining_time":8.256661747},
{"learn":[0.208783991],"iteration":333,"passed_time":4.133209629,"remaining_time":8.2416695},
{"learn":[0.2085618867],"iteration":334,"passed_time":4.145321373,"remaining_time":8.228772277},
{"learn":[0.2082474548],"iteration":335,"passed_time":4.156774936,"remaining_time":8.214579041},
{"learn":[0.20805181],"iteration":336,"passed_time":4.169554211,"remaining_time":8.203010214},
{"learn":[0.2077147962],"iteration":337,"passed_time":4.183361616,"remaining_time":8.193447899},
{"learn":[0.2074947746],"iteration":338,"passed_time":4.195849502,"remaining_time":8.181287671},
{"learn":[0.2071330184],"iteration":339,"passed_time":4.208864115,"remaining_time":8.170147987},
{"learn":[0.2066922483],"iteration":340,"passed_time":4.220717198,"remaining_time":8.156752591},
{"learn":[0.2063286127],"iteration":341,"passed_time":4.232308711,"remaining_time":8.142862959},
{"learn":[0.2058597377],"iteration":342,"passed_time":4.244540692,"remaining_time":8.130213512},
{"learn":[0.2054404723],"iteration":343,"passed_time":4.25576484,"remaining_time":8.115644579},
{"learn":[0.2050780246],"iteration":344,"passed_time":4.269169619,"remaining_time":8.105235074},
{"learn":[0.2047890698],"iteration":345,"passed_time":4.281182603,"remaining_time":8.092177521},
{"learn":[0.2047880315],"iteration":346,"passed_time":4.286077414,"remaining_time":8.065730695},
{"learn":[0.2043489726],"iteration":347,"passed_time":4.301228386,"remaining_time":8.058623298},
{"learn":[0.2039263403],"iteration":348,"passed_time":4.31349385,"remaining_time":8.046087383},
{"learn":[0.2033231363],"iteration":349,"passed_time":4.325419627,"remaining_time":8.032922164},
{"learn":[0.2027766092],"iteration":350,"passed_time":4.337938882,"remaining_time":8.020861352},
{"learn":[0.2023636337],"iteration":351,"passed_time":4.350159937,"remaining_time":8.008248974},
{"learn":[0.2019878187],"iteration":352,"passed_time":4.362175365,"remaining_time":7.99526193},
{"learn":[0.2017328311],"iteration":353,"passed_time":4.374389264,"remaining_time":7.982642555},
{"learn":[0.2015346751],"iteration":354,"passed_time":4.386740869,"remaining_time":7.970275663},
{"learn":[0.2010663749],"iteration":355,"passed_time":4.399891105,"remaining_time":7.959353572},
{"learn":[0.2006903129],"iteration":356,"passed_time":4.41209315,"remaining_time":7.946711191},
{"learn":[0.2005080679],"iteration":357,"passed_time":4.423975148,"remaining_time":7.933497332},
{"learn":[0.2000212219],"iteration":358,"passed_time":4.435755255,"remaining_time":7.920108965},
{"learn":[0.1995854791],"iteration":359,"passed_time":4.448215798,"remaining_time":7.907939197},
{"learn":[0.1995182689],"iteration":360,"passed_time":4.454599818,"remaining_time":7.885011866},
{"learn":[0.1992384676],"iteration":361,"passed_time":4.466397501,"remaining_time":7.871717142},
{"learn":[0.1988202185],"iteration":362,"passed_time":4.478084279,"remaining_time":7.858236049},
{"learn":[0.1983081022],"iteration":363,"passed_time":4.490055447,"remaining_time":7.845261716},
{"learn":[0.1980478576],"iteration":364,"passed_time":4.504052085,"remaining_time":7.835816642},
{"learn":[0.1978470068],"iteration":365,"passed_time":4.516872941,"remaining_time":7.824309957},
{"learn":[0.1973017776],"iteration":366,"passed_time":4.528399968,"remaining_time":7.810564522},
{"learn":[0.1970030122],"iteration":367,"passed_time":4.540150914,"remaining_time":7.7972157},
{"learn":[0.1965358445],"iteration":368,"passed_time":4.553049591,"remaining_time":7.78583819},
{"learn":[0.1961501137],"iteration":369,"passed_time":4.565523839,"remaining_time":7.773729779},
{"learn":[0.195862586],"iteration":370,"passed_time":4.578727841,"remaining_time":7.762856637},
{"learn":[0.1954803107],"iteration":371,"passed_time":4.591184653,"remaining_time":7.750709576},
{"learn":[0.1952823578],"iteration":372,"passed_time":4.6047127,"remaining_time":7.740361563},
{"learn":[0.1951001701],"iteration":373,"passed_time":4.61720183,"remaining_time":7.728257608},
{"learn":[0.1948367772],"iteration":374,"passed_time":4.629295142,"remaining_time":7.715491903},
{"learn":[0.1943570814],"iteration":375,"passed_time":4.641285407,"remaining_time":7.70255876},
{"learn":[0.1939022019],"iteration":376,"passed_time":4.653231345,"remaining_time":7.689557368},
{"learn":[0.1935159932],"iteration":377,"passed_time":4.665483287,"remaining_time":7.677065091},
{"learn":[0.1933132378],"iteration":378,"passed_time":4.679021932,"remaining_time":7.666682373},
{"learn":[0.1929931924],"iteration":379,"passed_time":4.692320207,"remaining_time":7.655890864},
{"learn":[0.1927085512],"iteration":380,"passed_time":4.705817934,"remaining_time":7.64541024},
{"learn":[0.1921330681],"iteration":381,"passed_time":4.718054119,"remaining_time":7.632872894},
{"learn":[0.191608031],"iteration":382,"passed_time":4.73044763,"remaining_time":7.620590568},
{"learn":[0.1913150401],"iteration":383,"passed_time":4.74242802,"remaining_time":7.607644949},
{"learn":[0.1909665804],"iteration":384,"passed_time":4.75435615,"remaining_time":7.594620863},
{"learn":[0.1907148749],"iteration":385,"passed_time":4.767140061,"remaining_time":7.582963724},
{"learn":[0.1904019843],"iteration":386,"passed_time":4.779247663,"remaining_time":7.570229503},
{"learn":[0.1901333053],"iteration":387,"passed_time":4.79172612,"remaining_time":7.558083467},
{"learn":[0.1897762907],"iteration":388,"passed_time":4.803724404,"remaining_time":7.545181519},
{"learn":[0.1894012415],"iteration":389,"passed_time":4.816718087,"remaining_time":7.533841111},
{"learn":[0.1891848463],"iteration":390,"passed_time":4.830134265,"remaining_time":7.5231503},
{"learn":[0.1888602061],"iteration":391,"passed_time":4.84276468,"remaining_time":7.51122685},
{"learn":[0.1886988437],"iteration":392,"passed_time":4.854549375,"remaining_time":7.497993565},
{"learn":[0.1883910694],"iteration":393,"passed_time":4.866454325,"remaining_time":7.484952591},
{"learn":[0.1880613776],"iteration":394,"passed_time":4.877692076,"remaining_time":7.470895458},
{"learn":[0.1877957944],"iteration":395,"passed_time":4.890253679,"remaining_time":7.458871774},
{"learn":[0.1872601251],"iteration":396,"passed_time":4.902097999,"remaining_time":7.445755902},
{"learn":[0.1870394361],"iteration":397,"passed_time":4.914959336,"remaining_time":7.434184725},
{"learn":[0.1866812667],"iteration":398,"passed_time":4.927516839,"remaining_time":7.422149424},
{"learn":[0.186316524],"iteration":399,"passed_time":4.939901991,"remaining_time":7.409852986},
{"learn":[0.1859994501],"iteration":400,"passed_time":4.951259627,"remaining_time":7.396021238},
{"learn":[0.185729523],"iteration":401,"passed_time":4.964817707,"remaining_time":7.385475096},
{"learn":[0.1853804713],"iteration":402,"passed_time":4.977804602,"remaining_time":7.374067859},
{"learn":[0.1851580257],"iteration":403,"passed_time":4.991372137,"remaining_time":7.36350939},
{"learn":[0.1847993991],"iteration":404,"passed_time":5.003177227,"remaining_time":7.35034679},
{"learn":[0.1845941905],"iteration":405,"passed_time":5.017741621,"remaining_time":7.341227889},
{"learn":[0.1844254092],"iteration":406,"passed_time":5.031569475,"remaining_time":7.331009088},
{"learn":[0.1840806],"iteration":407,"passed_time":5.043493295,"remaining_time":7.318009879},
{"learn":[0.1835577196],"iteration":408,"passed_time":5.056802998,"remaining_time":7.307018514},
{"learn":[0.1832539602],"iteration":409,"passed_time":5.068443058,"remaining_time":7.293613181},
{"learn":[0.1830369147],"iteration":410,"passed_time":5.078827794,"remaining_time":7.278417448},
{"learn":[0.1828460903],"iteration":411,"passed_time":5.090788262,"remaining_time":7.265493927},
{"learn":[0.1826726592],"iteration":412,"passed_time":5.103184457,"remaining_time":7.253194374},
{"learn":[0.1823444843],"iteration":413,"passed_time":5.115449468,"remaining_time":7.240708667},
{"learn":[0.1820800611],"iteration":414,"passed_time":5.130791698,"remaining_time":7.232561791},
{"learn":[0.1817195763],"iteration":415,"passed_time":5.145797004,"remaining_time":7.223907333},
{"learn":[0.1813800381],"iteration":416,"passed_time":5.158870474,"remaining_time":7.21252155},
{"learn":[0.1811089415],"iteration":417,"passed_time":5.171139392,"remaining_time":7.200007479},
{"learn":[0.1809514851],"iteration":418,"passed_time":5.184674628,"remaining_time":7.189250499},
{"learn":[0.1808940922],"iteration":419,"passed_time":5.191608169,"remaining_time":7.169363662},
{"learn":[0.1806943702],"iteration":420,"passed_time":5.203597054,"remaining_time":7.15649096},
{"learn":[0.1802743537],"iteration":421,"passed_time":5.216683669,"remaining_time":7.145125973},
{"learn":[0.1799899911],"iteration":422,"passed_time":5.230427752,"remaining_time":7.134649676},
{"learn":[0.1796772359],"iteration":423,"passed_time":5.242465039,"remaining_time":7.121839299},
{"learn":[0.1794429388],"iteration":424,"passed_time":5.254710566,"remaining_time":7.109314296},
{"learn":[0.1790382086],"iteration":425,"passed_time":5.265988437,"remaining_time":7.095486767},
{"learn":[0.1788284572],"iteration":426,"passed_time":5.279795649,"remaining_time":7.085065355},
{"learn":[0.1788271551],"iteration":427,"passed_time":5.285455614,"remaining_time":7.063739746},
{"learn":[0.1785537345],"iteration":428,"passed_time":5.296754697,"remaining_time":7.049992848},
{"learn":[0.1781716968],"iteration":429,"passed_time":5.308408707,"remaining_time":7.03672782},
{"learn":[0.1778338924],"iteration":430,"passed_time":5.321826504,"remaining_time":7.025798796},
{"learn":[0.1774544845],"iteration":431,"passed_time":5.334191354,"remaining_time":7.013473817},
{"learn":[0.1770994252],"iteration":432,"passed_time":5.34703562,"remaining_time":7.001776435},
{"learn":[0.1768581109],"iteration":433,"passed_time":5.359459486,"remaining_time":6.989525505},
{"learn":[0.1764758044],"iteration":434,"passed_time":5.37297629,"remaining_time":6.978693342},
{"learn":[0.1763430633],"iteration":435,"passed_time":5.378991754,"remaining_time":6.958145297},
{"learn":[0.1761942499],"iteration":436,"passed_time":5.390669627,"remaining_time":6.94495881},
{"learn":[0.176039966],"iteration":437,"passed_time":5.402322151,"remaining_time":6.931746688},
{"learn":[0.1758551181],"iteration":438,"passed_time":5.413681581,"remaining_time":6.918167122},
{"learn":[0.175513908],"iteration":439,"passed_time":5.425295771,"remaining_time":6.904921891},
{"learn":[0.1751968297],"iteration":440,"passed_time":5.438020359,"remaining_time":6.893091566},
{"learn":[0.174882419],"iteration":441,"passed_time":5.449584222,"remaining_time":6.879791845},
{"learn":[0.1746532748],"iteration":442,"passed_time":5.461346037,"remaining_time":6.866748854},
{"learn":[0.1745198312],"iteration":443,"passed_time":5.473131751,"remaining_time":6.853741562},
{"learn":[0.1742475204],"iteration":444,"passed_time":5.484441664,"remaining_time":6.840146345},
{"learn":[0.1737824356],"iteration":445,"passed_time":5.496571965,"remaining_time":6.827580423},
{"learn":[0.1735537302],"iteration":446,"passed_time":5.509167868,"remaining_time":6.815592463},
{"learn":[0.1734927132],"iteration":447,"passed_time":5.518043737,"remaining_time":6.799018176},
{"learn":[0.1732734283],"iteration":448,"passed_time":5.529476412,"remaining_time":6.78561582},
{"learn":[0.1730469823],"iteration":449,"passed_time":5.542439039,"remaining_time":6.774092159},
{"learn":[0.1730176796],"iteration":450,"passed_time":5.551356035,"remaining_time":6.757637391},
{"learn":[0.1728020096],"iteration":451,"passed_time":5.56287676,"remaining_time":6.744372709},
{"learn":[0.1724493409],"iteration":452,"passed_time":5.574629628,"remaining_time":6.731396041},
{"learn":[0.1720863896],"iteration":453,"passed_time":5.586886623,"remaining_time":6.719031049},
{"learn":[0.1717428229],"iteration":454,"passed_time":5.598789291,"remaining_time":6.706242118},
{"learn":[0.1716567852],"iteration":455,"passed_time":5.609172116,"remaining_time":6.691643928},
{"learn":[0.1716348528],"iteration":456,"passed_time":5.614200763,"remaining_time":6.670702438},
{"learn":[0.1714039064],"iteration":457,"passed_time":5.627241647,"remaining_time":6.659312167},
{"learn":[0.171243811],"iteration":458,"passed_time":5.641427812,"remaining_time":6.649264589},
{"learn":[0.1709991645],"iteration":459,"passed_time":5.653257746,"remaining_time":6.636433006},
{"learn":[0.1708229634],"iteration":460,"passed_time":5.664611673,"remaining_time":6.623049223},
{"learn":[0.1705788043],"iteration":461,"passed_time":5.678073943,"remaining_time":6.612129397},
{"learn":[0.1704501632],"iteration":462,"passed_time":5.691073336,"remaining_time":6.600661731},
{"learn":[0.170175296],"iteration":463,"passed_time":5.703807293,"remaining_time":6.588880839},
{"learn":[0.1697716607],"iteration":464,"passed_time":5.71542665,"remaining_time":6.575813457},
{"learn":[0.1694849188],"iteration":465,"passed_time":5.727210127,"remaining_time":6.56294036},
{"learn":[0.169436854],"iteration":466,"passed_time":5.732747635,"remaining_time":6.542943232},
{"learn":[0.1691586274],"iteration":467,"passed_time":5.743630904,"remaining_time":6.529084703},
{"learn":[0.1689951999],"iteration":468,"passed_time":5.756529328,"remaining_time":6.517520412},
{"learn":[0.1687445363],"iteration":469,"passed_time":5.768993222,"remaining_time":6.505460442},
{"learn":[0.1684025376],"iteration":470,"passed_time":5.780881896,"remaining_time":6.492752703},
{"learn":[0.1682238514],"iteration":471,"passed_time":5.792720692,"remaining_time":6.479992638},
{"learn":[0.167901614],"iteration":472,"passed_time":5.804412704,"remaining_time":6.467072928},
{"learn":[0.1676136655],"iteration":473,"passed_time":5.816562218,"remaining_time":6.45466609},
{"learn":[0.1672626623],"iteration":474,"passed_time":5.828343145,"remaining_time":6.44185295},
{"learn":[0.1671503619],"iteration":475,"passed_time":5.840250738,"remaining_time":6.429183586},
{"learn":[0.1668833849],"iteration":476,"passed_time":5.853846614,"remaining_time":6.41836851},
{"learn":[0.1665599278],"iteration":477,"passed_time":5.865780212,"remaining_time":6.405726508},
{"learn":[0.166369686],"iteration":478,"passed_time":5.877045272,"remaining_time":6.392360306},
{"learn":[0.1661097325],"iteration":479,"passed_time":5.889053541,"remaining_time":6.379808002},
{"learn":[0.1658930952],"iteration":480,"passed_time":5.900821931,"remaining_time":6.366999131},
{"learn":[0.1655781385],"iteration":481,"passed_time":5.912012796,"remaining_time":6.353573918},
{"learn":[0.1653432131],"iteration":482,"passed_time":5.923648802,"remaining_time":6.340634432},
{"learn":[0.16516916],"iteration":483,"passed_time":5.935740501,"remaining_time":6.328186154},
{"learn":[0.1651015906],"iteration":484,"passed_time":5.943492215,"remaining_time":6.311130909},
{"learn":[0.1648357352],"iteration":485,"passed_time":5.955758973,"remaining_time":6.298889119},
{"learn":[0.1645440141],"iteration":486,"passed_time":5.969576142,"remaining_time":6.288280412},
{"learn":[0.1643054809],"iteration":487,"passed_time":5.981270322,"remaining_time":6.275431158},
{"learn":[0.1640085909],"iteration":488,"passed_time":5.992015052,"remaining_time":6.261594462},
{"learn":[0.1637641402],"iteration":489,"passed_time":6.004195062,"remaining_time":6.249264248},
{"learn":[0.1634576867],"iteration":490,"passed_time":6.01698497,"remaining_time":6.237566904},
{"learn":[0.1632293956],"iteration":491,"passed_time":6.028418401,"remaining_time":6.224464528},
{"learn":[0.1629926138],"iteration":492,"passed_time":6.040376729,"remaining_time":6.211908725},
{"learn":[0.1628365202],"iteration":493,"passed_time":6.052420549,"remaining_time":6.199442911},
{"learn":[0.1626644946],"iteration":494,"passed_time":6.065110241,"remaining_time":6.18763772},
{"learn":[0.1623709063],"iteration":495,"passed_time":6.077442405,"remaining_time":6.17546567},
{"learn":[0.1621293176],"iteration":496,"passed_time":6.089497116,"remaining_time":6.163012172},
{"learn":[0.1618968324],"iteration":497,"passed_time":6.10131473,"remaining_time":6.150321274},
{"learn":[0.1617276702],"iteration":498,"passed_time":6.113117419,"remaining_time":6.137618891},
{"learn":[0.1614168081],"iteration":499,"passed_time":6.124944249,"remaining_time":6.124944249},
{"learn":[0.1610077672],"iteration":500,"passed_time":6.137851244,"remaining_time":6.113348844},
{"learn":[0.1608375662],"iteration":501,"passed_time":6.149815575,"remaining_time":6.10081306},
{"learn":[0.1606242837],"iteration":502,"passed_time":6.161773111,"remaining_time":6.088272835},
{"learn":[0.1603684324],"iteration":503,"passed_time":6.174876773,"remaining_time":6.076862856},
{"learn":[0.1601259732],"iteration":504,"passed_time":6.186668068,"remaining_time":6.064159789},
{"learn":[0.1599195669],"iteration":505,"passed_time":6.198969537,"remaining_time":6.051958402},
{"learn":[0.1597831077],"iteration":506,"passed_time":6.210079699,"remaining_time":6.038598208},
{"learn":[0.159552175],"iteration":507,"passed_time":6.222657217,"remaining_time":6.026668013},
{"learn":[0.159345604],"iteration":508,"passed_time":6.23549286,"remaining_time":6.014984272},
{"learn":[0.1593229435],"iteration":509,"passed_time":6.242242124,"remaining_time":5.997448316},
{"learn":[0.1591029152],"iteration":510,"passed_time":6.254626511,"remaining_time":5.985347092},
{"learn":[0.1587807065],"iteration":511,"passed_time":6.266751226,"remaining_time":5.972997263},
{"learn":[0.1586145198],"iteration":512,"passed_time":6.279909414,"remaining_time":5.961629405},
{"learn":[0.1584932413],"iteration":513,"passed_time":6.290395663,"remaining_time":5.947728195},
{"learn":[0.1583459089],"iteration":514,"passed_time":6.302857278,"remaining_time":5.935700543},
{"learn":[0.1581206835],"iteration":515,"passed_time":6.314811479,"remaining_time":5.923195264},
{"learn":[0.1579700831],"iteration":516,"passed_time":6.326382859,"remaining_time":5.91033447},
{"learn":[0.1579518132],"iteration":517,"passed_time":6.333246704,"remaining_time":5.893098284},
{"learn":[0.157619296],"iteration":518,"passed_time":6.345772159,"remaining_time":5.881149149},
{"learn":[0.1573950938],"iteration":519,"passed_time":6.357646769,"remaining_time":5.868597018},
{"learn":[0.1571718226],"iteration":520,"passed_time":6.370472842,"remaining_time":5.856922248},
{"learn":[0.1570178816],"iteration":521,"passed_time":6.384479013,"remaining_time":5.846323694},
{"learn":[0.1566068094],"iteration":522,"passed_time":6.405699416,"remaining_time":5.842291819},
{"learn":[0.1565950773],"iteration":523,"passed_time":6.413281494,"remaining_time":5.825805327},
{"learn":[0.1562896828],"iteration":524,"passed_time":6.426023906,"remaining_time":5.814021629},
{"learn":[0.1560312918],"iteration":525,"passed_time":6.438409582,"remaining_time":5.801912817},
{"learn":[0.15590364],"iteration":526,"passed_time":6.451243765,"remaining_time":5.790205504},
{"learn":[0.1557095975],"iteration":527,"passed_time":6.463478375,"remaining_time":5.777957942},
{"learn":[0.1554569596],"iteration":528,"passed_time":6.475950869,"remaining_time":5.765922229},
{"learn":[0.1552754552],"iteration":529,"passed_time":6.489086401,"remaining_time":5.754472846},
{"learn":[0.1549261029],"iteration":530,"passed_time":6.50212617,"remaining_time":5.742932531},
{"learn":[0.1547012689],"iteration":531,"passed_time":6.51368756,"remaining_time":5.730086049},
{"learn":[0.1546381352],"iteration":532,"passed_time":6.522933214,"remaining_time":5.715215405},
{"learn":[0.1546059463],"iteration":533,"passed_time":6.531954178,"remaining_time":5.700169751},
{"learn":[0.1544739236],"iteration":534,"passed_time":6.544541316,"remaining_time":5.68824619},
{"learn":[0.1542334744],"iteration":535,"passed_time":6.556745207,"remaining_time":5.675988389},
{"learn":[0.1539936703],"iteration":536,"passed_time":6.568759184,"remaining_time":5.663567043},
{"learn":[0.1537146545],"iteration":537,"passed_time":6.580565681,"remaining_time":5.650969042},
{"learn":[0.1535127873],"iteration":538,"passed_time":6.592571956,"remaining_time":5.638544845},
{"learn":[0.1532910545],"iteration":539,"passed_time":6.605268124,"remaining_time":5.626709883},
{"learn":[0.1530341767],"iteration":540,"passed_time":6.617850886,"remaining_time":5.614775521},
{"learn":[0.1527906881],"iteration":541,"passed_time":6.629737698,"remaining_time":5.602250675},
{"learn":[0.1525706462],"iteration":542,"passed_time":6.641782587,"remaining_time":5.58986122},
{"learn":[0.1523783234],"iteration":543,"passed_time":6.653300652,"remaining_time":5.577031429},
{"learn":[0.152217616],"iteration":544,"passed_time":6.667066221,"remaining_time":5.566082808},
{"learn":[0.1522176156],"iteration":545,"passed_time":6.670205794,"remaining_time":5.546288334},
{"learn":[0.1519780885],"iteration":546,"passed_time":6.682547912,"remaining_time":5.534175876},
{"learn":[0.1517504405],"iteration":547,"passed_time":6.695787635,"remaining_time":5.522802939},
{"learn":[0.1515425152],"iteration":548,"passed_time":6.707059323,"remaining_time":5.509806475},
{"learn":[0.1511906738],"iteration":549,"passed_time":6.718172036,"remaining_time":5.496686211},
{"learn":[0.1510333356],"iteration":550,"passed_time":6.730141473,"remaining_time":5.484271364},
{"learn":[0.150919561],"iteration":551,"passed_time":6.74183036,"remaining_time":5.471630437},
{"learn":[0.1506668617],"iteration":552,"passed_time":6.752909879,"remaining_time":5.45850039},
{"learn":[0.1505184633],"iteration":553,"passed_time":6.76472857,"remaining_time":5.44597282},
{"learn":[0.1503928177],"iteration":554,"passed_time":6.7771231,"remaining_time":5.433909513},
{"learn":[0.1501963223],"iteration":555,"passed_time":6.789115416,"remaining_time":5.421523822},
{"learn":[0.1499552477],"iteration":556,"passed_time":6.802287406,"remaining_time":5.410077776},
{"learn":[0.1498652253],"iteration":557,"passed_time":6.815056481,"remaining_time":5.398306388},
{"learn":[0.1496839879],"iteration":558,"passed_time":6.827381896,"remaining_time":5.386181424},
{"learn":[0.1494364564],"iteration":559,"passed_time":6.838978096,"remaining_time":5.37348279},
{"learn":[0.1493512151],"iteration":560,"passed_time":6.848705831,"remaining_time":5.359325954},
{"learn":[0.149332686],"iteration":561,"passed_time":6.854998431,"remaining_time":5.342507674},
{"learn":[0.1490869763],"iteration":562,"passed_time":6.866606591,"remaining_time":5.329852718},
{"learn":[0.148860108],"iteration":563,"passed_time":6.87869559,"remaining_time":5.317573187},
{"learn":[0.1487321471],"iteration":564,"passed_time":6.890666838,"remaining_time":5.305203672},
{"learn":[0.1484902284],"iteration":565,"passed_time":6.901870512,"remaining_time":5.292247},
{"learn":[0.1483370555],"iteration":566,"passed_time":6.933010645,"remaining_time":5.294521357},
{"learn":[0.1480910113],"iteration":567,"passed_time":6.946159808,"remaining_time":5.282994783},
{"learn":[0.1479027727],"iteration":568,"passed_time":6.958648323,"remaining_time":5.270962086},
{"learn":[0.1477771991],"iteration":569,"passed_time":6.96960838,"remaining_time":5.257774743},
{"learn":[0.1477018743],"iteration":570,"passed_time":6.981566268,"remaining_time":5.245344885},
{"learn":[0.1475279757],"iteration":571,"passed_time":6.993757227,"remaining_time":5.233091072},
{"learn":[0.1473911508],"iteration":572,"passed_time":7.005666475,"remaining_time":5.220627548},
{"learn":[0.1472018971],"iteration":573,"passed_time":7.017979285,"remaining_time":5.208465463},
{"learn":[0.1471709418],"iteration":574,"passed_time":7.025244055,"remaining_time":5.192571693},
{"learn":[0.1469599744],"iteration":575,"passed_time":7.036492868,"remaining_time":5.179640583},
{"learn":[0.1467900605],"iteration":576,"passed_time":7.049407248,"remaining_time":5.167936336},
{"learn":[0.1464463145],"iteration":577,"passed_time":7.061611004,"remaining_time":5.155709072},
{"learn":[0.1463750959],"iteration":578,"passed_time":7.073283083,"remaining_time":5.143095299},
{"learn":[0.1461482421],"iteration":579,"passed_time":7.084287854,"remaining_time":5.130001549},
{"learn":[0.145927182],"iteration":580,"passed_time":7.096731519,"remaining_time":5.117952679},
{"learn":[0.1457574339],"iteration":581,"passed_time":7.108945553,"remaining_time":5.105737528},
{"learn":[0.1455006979],"iteration":582,"passed_time":7.120309055,"remaining_time":5.092914024},
{"learn":[0.145192206],"iteration":583,"passed_time":7.13280499,"remaining_time":5.080902184},
{"learn":[0.1449595958],"iteration":584,"passed_time":7.144653292,"remaining_time":5.068429259},
{"learn":[0.1448253978],"iteration":585,"passed_time":7.156194476,"remaining_time":5.05574149},
{"learn":[0.1446328605],"iteration":586,"passed_time":7.167960769,"remaining_time":5.043216009},
{"learn":[0.1444543666],"iteration":587,"passed_time":7.180305,"remaining_time":5.031098061},
{"learn":[0.1442266542],"iteration":588,"passed_time":7.192838756,"remaining_time":5.019111593},
{"learn":[0.1440284621],"iteration":589,"passed_time":7.204337364,"remaining_time":5.006403931},
{"learn":[0.143872322],"iteration":590,"passed_time":7.216098744,"remaining_time":4.99388221},
{"learn":[0.1437315523],"iteration":591,"passed_time":7.229189782,"remaining_time":4.982279444},
{"learn":[0.1435705186],"iteration":592,"passed_time":7.237857484,"remaining_time":4.967635744},
{"learn":[0.1435265333],"iteration":593,"passed_time":7.249253421,"remaining_time":4.954876917},
{"learn":[0.1433233006],"iteration":594,"passed_time":7.261351884,"remaining_time":4.942600862},
{"learn":[0.1431564801],"iteration":595,"passed_time":7.275076201,"remaining_time":4.931427492},
{"learn":[0.143035603],"iteration":596,"passed_time":7.287529256,"remaining_time":4.919387421},
{"learn":[0.1428888515],"iteration":597,"passed_time":7.299074978,"remaining_time":4.906736022},
{"learn":[0.1426958596],"iteration":598,"passed_time":7.311330477,"remaining_time":4.894563475},
{"learn":[0.1424840926],"iteration":599,"passed_time":7.324892274,"remaining_time":4.883261516},
{"learn":[0.1423872845],"iteration":600,"passed_time":7.336596803,"remaining_time":4.870719009},
{"learn":[0.1423710594],"iteration":601,"passed_time":7.341253167,"remaining_time":4.853519536},
{"learn":[0.1422109103],"iteration":602,"passed_time":7.35282486,"remaining_time":4.840914543},
{"learn":[0.1421932246],"iteration":603,"passed_time":7.359191024,"remaining_time":4.824900075},
{"learn":[0.1420637603],"iteration":604,"passed_time":7.371738328,"remaining_time":4.812953123},
{"learn":[0.1418343982],"iteration":605,"passed_time":7.383973484,"remaining_time":4.800801242},
{"learn":[0.1416623347],"iteration":606,"passed_time":7.395899934,"remaining_time":4.788449216},
{"learn":[0.1415549488],"iteration":607,"passed_time":7.407606684,"remaining_time":4.775956941},
{"learn":[0.1414658132],"iteration":608,"passed_time":7.4173491,"remaining_time":4.762206072},
{"learn":[0.1412337021],"iteration":609,"passed_time":7.429633824,"remaining_time":4.750093756},
{"learn":[0.1409920955],"iteration":610,"passed_time":7.450748979,"remaining_time":4.743602869},
{"learn":[0.1408438395],"iteration":611,"passed_time":7.462144643,"remaining_time":4.730902159},
{"learn":[0.1408145793],"iteration":612,"passed_time":7.487868995,"remaining_time":4.727251715},
{"learn":[0.1406551822],"iteration":613,"passed_time":7.50484103,"remaining_time":4.718027097},
{"learn":[0.140491489],"iteration":614,"passed_time":7.518077883,"remaining_time":4.706439},
{"learn":[0.1403536979],"iteration":615,"passed_time":7.530993023,"remaining_time":4.694645001},
{"learn":[0.1401631012],"iteration":616,"passed_time":7.546003924,"remaining_time":4.684148303},
{"learn":[0.1401631002],"iteration":617,"passed_time":7.549691903,"remaining_time":4.666638037},
{"learn":[0.1400379336],"iteration":618,"passed_time":7.561202586,"remaining_time":4.653987375},
{"learn":[0.1399086299],"iteration":619,"passed_time":7.573495055,"remaining_time":4.64181955},
{"learn":[0.1398165661],"iteration":620,"passed_time":7.58566003,"remaining_time":4.629573512},
{"learn":[0.1396345512],"iteration":621,"passed_time":7.597232519,"remaining_time":4.616967672},
{"learn":[0.1394735007],"iteration":622,"passed_time":7.609238285,"remaining_time":4.604627341},
{"learn":[0.1392926741],"iteration":623,"passed_time":7.62167213,"remaining_time":4.592546027},
{"learn":[0.1391446024],"iteration":624,"passed_time":7.633087603,"remaining_time":4.579852562},
{"learn":[0.139088214],"iteration":625,"passed_time":7.646425144,"remaining_time":4.568311508},
{"learn":[0.1388845401],"iteration":626,"passed_time":7.659596567,"remaining_time":4.5566659},
{"learn":[0.1386698884],"iteration":627,"passed_time":7.671597753,"remaining_time":4.544322236},
{"learn":[0.1385616368],"iteration":628,"passed_time":7.68315334,"remaining_time":4.531716835},
{"learn":[0.1383736523],"iteration":629,"passed_time":7.694935589,"remaining_time":4.519247885},
{"learn":[0.138230925],"iteration":630,"passed_time":7.70676248,"remaining_time":4.506807219},
{"learn":[0.1381328288],"iteration":631,"passed_time":7.71899441,"remaining_time":4.49460434},
{"learn":[0.1380366027],"iteration":632,"passed_time":7.730488433,"remaining_time":4.481973546},
{"learn":[0.1379368963],"iteration":633,"passed_time":7.742793266,"remaining_time":4.469814409},
{"learn":[0.1378595617],"iteration":634,"passed_time":7.756033345,"remaining_time":4.458192395},
{"learn":[0.1377335968],"iteration":635,"passed_time":7.769255655,"remaining_time":4.446555123},
{"learn":[0.1376465349],"iteration":636,"passed_time":7.780679609,"remaining_time":4.433888066},
{"learn":[0.1374381949],"iteration":637,"passed_time":7.793095168,"remaining_time":4.42178754},
{"learn":[0.1373086465],"iteration":638,"passed_time":7.805225224,"remaining_time":4.409524735},
{"learn":[0.1370956308],"iteration":639,"passed_time":7.81712907,"remaining_time":4.397135102},
{"learn":[0.1368366044],"iteration":640,"passed_time":7.828493518,"remaining_time":4.384444888},
{"learn":[0.1367930895],"iteration":641,"passed_time":7.840361611,"remaining_time":4.372039652},
{"learn":[0.1366204824],"iteration":642,"passed_time":7.854168837,"remaining_time":4.360712714},
{"learn":[0.1363626224],"iteration":643,"passed_time":7.867100375,"remaining_time":4.348893996},
{"learn":[0.1361666227],"iteration":644,"passed_time":7.878870863,"remaining_time":4.336432801},
{"learn":[0.1359936177],"iteration":645,"passed_time":7.891397842,"remaining_time":4.324388291},
{"learn":[0.1359115083],"iteration":646,"passed_time":7.903517275,"remaining_time":4.312119935},
{"learn":[0.1356573581],"iteration":647,"passed_time":7.915373912,"remaining_time":4.299709286},
{"learn":[0.1354818809],"iteration":648,"passed_time":7.927432699,"remaining_time":4.287409672},
{"learn":[0.1353988445],"iteration":649,"passed_time":7.934270132,"remaining_time":4.272299302},
{"learn":[0.1351470517],"iteration":650,"passed_time":7.945853442,"remaining_time":4.259758604},
{"learn":[0.1349313766],"iteration":651,"passed_time":7.959022983,"remaining_time":4.248067482},
{"learn":[0.1348343818],"iteration":652,"passed_time":7.97178589,"remaining_time":4.236155748},
{"learn":[0.1346459837],"iteration":653,"passed_time":7.983612352,"remaining_time":4.223745984},
{"learn":[0.1345251005],"iteration":654,"passed_time":7.995377358,"remaining_time":4.211305631},
{"learn":[0.1342934189],"iteration":655,"passed_time":8.007327433,"remaining_time":4.198964386},
{"learn":[0.1342170232],"iteration":656,"passed_time":8.01967867,"remaining_time":4.186833765},
{"learn":[0.1341963937],"iteration":657,"passed_time":8.026091705,"remaining_time":4.171616053},
{"learn":[0.1339366574],"iteration":658,"passed_time":8.038013737,"remaining_time":4.159275697},
{"learn":[0.1337136145],"iteration":659,"passed_time":8.050346341,"remaining_time":4.147148115},
{"learn":[0.1335514968],"iteration":660,"passed_time":8.064516343,"remaining_time":4.135962239},
{"learn":[0.1333910681],"iteration":661,"passed_time":8.07626669,"remaining_time":4.123531935},
{"learn":[0.1333177773],"iteration":662,"passed_time":8.088195601,"remaining_time":4.111194446},
{"learn":[0.1331423483],"iteration":663,"passed_time":8.10046143,"remaining_time":4.099028675},
{"learn":[0.1330486301],"iteration":664,"passed_time":8.112008351,"remaining_time":4.086500447},
{"learn":[0.1329598482],"iteration":665,"passed_time":8.124230347,"remaining_time":4.074313718},
{"learn":[0.1327853845],"iteration":666,"passed_time":8.136296737,"remaining_time":4.062049196},
{"learn":[0.1326797845],"iteration":667,"passed_time":8.16003977,"remaining_time":4.055588628},
{"learn":[0.1325436088],"iteration":668,"passed_time":8.17390845,"remaining_time":4.044190878},
{"learn":[0.1323706369],"iteration":669,"passed_time":8.18594722,"remaining_time":4.031884452},
{"learn":[0.1321826721],"iteration":670,"passed_time":8.197751318,"remaining_time":4.019463761},
{"learn":[0.1320669006],"iteration":671,"passed_time":8.209380956,"remaining_time":4.006959752},
{"learn":[0.1319380204],"iteration":672,"passed_time":8.221914008,"remaining_time":3.994897296},
{"learn":[0.131853653],"iteration":673,"passed_time":8.234600734,"remaining_time":3.982907774},
{"learn":[0.1317317451],"iteration":674,"passed_time":8.246771913,"remaining_time":3.970667958},
{"learn":[0.1315516282],"iteration":675,"passed_time":8.259586113,"remaining_time":3.958736539},
{"learn":[0.1313313023],"iteration":676,"passed_time":8.275624787,"remaining_time":3.948340925},
{"learn":[0.1312140704],"iteration":677,"passed_time":8.288355481,"remaining_time":3.936357618},
{"learn":[0.130947649],"iteration":678,"passed_time":8.300621705,"remaining_time":3.924152529},
{"learn":[0.130818984],"iteration":679,"passed_time":8.312464828,"remaining_time":3.911748154},
{"learn":[0.1306652285],"iteration":680,"passed_time":8.324507777,"remaining_time":3.899439032},
{"learn":[0.1305593629],"iteration":681,"passed_time":8.336333006,"remaining_time":3.887029173},
{"learn":[0.1305078556],"iteration":682,"passed_time":8.348425261,"remaining_time":3.87474496},
{"learn":[0.1304572443],"iteration":683,"passed_time":8.356466736,"remaining_time":3.860589896},
{"learn":[0.1302694571],"iteration":684,"passed_time":8.370435438,"remaining_time":3.84917834},
{"learn":[0.1301034721],"iteration":685,"passed_time":8.383025381,"remaining_time":3.837128236},
{"learn":[0.1299762956],"iteration":686,"passed_time":8.394736122,"remaining_time":3.824675992},
{"learn":[0.1297543369],"iteration":687,"passed_time":8.407116598,"remaining_time":3.81252962},
{"learn":[0.1295517459],"iteration":688,"passed_time":8.41998676,"remaining_time":3.800603603},
{"learn":[0.1294492367],"iteration":689,"passed_time":8.431633844,"remaining_time":3.78812535},
{"learn":[0.1291682754],"iteration":690,"passed_time":8.443740477,"remaining_time":3.775855004},
{"learn":[0.1290244481],"iteration":691,"passed_time":8.455738496,"remaining_time":3.763536787},
{"learn":[0.1288923508],"iteration":692,"passed_time":8.469364368,"remaining_time":3.751940636},
{"learn":[0.1287989232],"iteration":693,"passed_time":8.481699448,"remaining_time":3.739769497},
{"learn":[0.1286576974],"iteration":694,"passed_time":8.494146149,"remaining_time":3.727646871},
{"learn":[0.1284322503],"iteration":695,"passed_time":8.506317775,"remaining_time":3.715403166},
{"learn":[0.1282361394],"iteration":696,"passed_time":8.518823849,"remaining_time":3.703305059},
{"learn":[0.1280497176],"iteration":697,"passed_time":8.531102578,"remaining_time":3.691107419},
{"learn":[0.1278939806],"iteration":698,"passed_time":8.543226838,"remaining_time":3.67884303},
{"learn":[0.1276844526],"iteration":699,"passed_time":8.555378973,"remaining_time":3.666590988},
{"learn":[0.1275531742],"iteration":700,"passed_time":8.567763972,"remaining_time":3.654438556},
{"learn":[0.1273656456],"iteration":701,"passed_time":8.580524996,"remaining_time":3.642445084},
{"learn":[0.1273231252],"iteration":702,"passed_time":8.590417659,"remaining_time":3.629237617},
{"learn":[0.1270194927],"iteration":703,"passed_time":8.602353967,"remaining_time":3.616898827},
{"learn":[0.126921218],"iteration":704,"passed_time":8.615030479,"remaining_time":3.60487091},
{"learn":[0.1268729586],"iteration":705,"passed_time":8.627157343,"remaining_time":3.592612265},
{"learn":[0.126710174],"iteration":706,"passed_time":8.6391197,"remaining_time":3.580285816},
{"learn":[0.1265909046],"iteration":707,"passed_time":8.652719703,"remaining_time":3.56863581},
{"learn":[0.1264565417],"iteration":708,"passed_time":8.665056442,"remaining_time":3.556461812},
{"learn":[0.1262747072],"iteration":709,"passed_time":8.677233947,"remaining_time":3.544222316},
{"learn":[0.1260930642],"iteration":710,"passed_time":8.68979969,"remaining_time":3.532140802},
{"learn":[0.1259168038],"iteration":711,"passed_time":8.701780603,"remaining_time":3.519821367},
{"learn":[0.1258593443],"iteration":712,"passed_time":8.713331772,"remaining_time":3.5073299},
{"learn":[0.1257352465],"iteration":713,"passed_time":8.724801064,"remaining_time":3.494808269},
{"learn":[0.1257270307],"iteration":714,"passed_time":8.73009196,"remaining_time":3.479826865},
{"learn":[0.1256035922],"iteration":715,"passed_time":8.74173902,"remaining_time":3.46739369},
{"learn":[0.125492967],"iteration":716,"passed_time":8.753336741,"remaining_time":3.454943232},
{"learn":[0.1254367041],"iteration":717,"passed_time":8.767600545,"remaining_time":3.443542275},
{"learn":[0.1253263642],"iteration":718,"passed_time":8.780761331,"remaining_time":3.431702273},
{"learn":[0.1252216908],"iteration":719,"passed_time":8.793408628,"remaining_time":3.419658911},
{"learn":[0.1250768893],"iteration":720,"passed_time":8.804591875,"remaining_time":3.407047341},
{"learn":[0.1249821351],"iteration":721,"passed_time":8.816718497,"remaining_time":3.394802967},
{"learn":[0.1249006585],"iteration":722,"passed_time":8.823234976,"remaining_time":3.380409528},
{"learn":[0.1246784969],"iteration":723,"passed_time":8.835163332,"remaining_time":3.368100939},
{"learn":[0.124521348],"iteration":724,"passed_time":8.847139794,"remaining_time":3.355811646},
{"learn":[0.1243933612],"iteration":725,"passed_time":8.859075572,"remaining_time":3.343507861},
{"learn":[0.124310948],"iteration":726,"passed_time":8.870473737,"remaining_time":3.331003205},
{"learn":[0.124204629],"iteration":727,"passed_time":8.883056073,"remaining_time":3.318944027},
{"learn":[0.1241048898],"iteration":728,"passed_time":8.896302428,"remaining_time":3.307130258},
{"learn":[0.1238659342],"iteration":729,"passed_time":8.907846647,"remaining_time":3.294683007},
{"learn":[0.1236731987],"iteration":730,"passed_time":8.91917676,"remaining_time":3.282159437},
{"learn":[0.123475018],"iteration":731,"passed_time":8.931230267,"remaining_time":3.269903978},
{"learn":[0.1234548162],"iteration":732,"passed_time":8.937868044,"remaining_time":3.255676354},
{"learn":[0.1233200138],"iteration":733,"passed_time":8.949773869,"remaining_time":3.243378541},
{"learn":[0.1232617682],"iteration":734,"passed_time":8.961839778,"remaining_time":3.231139512},
{"learn":[0.1231960626],"iteration":735,"passed_time":8.973907015,"remaining_time":3.218901429},
{"learn":[0.1229341856],"iteration":736,"passed_time":8.985405113,"remaining_time":3.206460712},
{"learn":[0.1229340639],"iteration":737,"passed_time":8.990708318,"remaining_time":3.191823278},
{"learn":[0.1227871371],"iteration":738,"passed_time":9.003299091,"remaining_time":3.179784929},
{"learn":[0.1226999244],"iteration":739,"passed_time":9.015445489,"remaining_time":3.167588956},
{"learn":[0.1224681396],"iteration":740,"passed_time":9.02795035,"remaining_time":3.155518409},
{"learn":[0.1223669318],"iteration":741,"passed_time":9.039560716,"remaining_time":3.143135667},
{"learn":[0.1222580131],"iteration":742,"passed_time":9.052309661,"remaining_time":3.131148833},
{"learn":[0.1221009422],"iteration":743,"passed_time":9.064263415,"remaining_time":3.118886336},
{"learn":[0.1219812317],"iteration":744,"passed_time":9.076759835,"remaining_time":3.106810413},
{"learn":[0.1218122323],"iteration":745,"passed_time":9.089041076,"remaining_time":3.094660098},
{"learn":[0.1215765014],"iteration":746,"passed_time":9.101737525,"remaining_time":3.082650059},
{"learn":[0.1213440886],"iteration":747,"passed_time":9.113775363,"remaining_time":3.070416299},
{"learn":[0.1212331719],"iteration":748,"passed_time":9.126047329,"remaining_time":3.058261522},
{"learn":[0.1210823586],"iteration":749,"passed_time":9.1532923,"remaining_time":3.051097433},
{"learn":[0.1209938263],"iteration":750,"passed_time":9.16661704,"remaining_time":3.039264505},
{"learn":[0.1209549669],"iteration":751,"passed_time":9.174246558,"remaining_time":3.025549397},
{"learn":[0.1207186445],"iteration":752,"passed_time":9.186155442,"remaining_time":3.013254176},
{"learn":[0.1206185507],"iteration":753,"passed_time":9.19805079,"remaining_time":3.000955563},
{"learn":[0.120468421],"iteration":754,"passed_time":9.211655286,"remaining_time":2.989212642},
{"learn":[0.1203335354],"iteration":755,"passed_time":9.224144828,"remaining_time":2.977104944},
{"learn":[0.1202621915],"iteration":756,"passed_time":9.235666995,"remaining_time":2.964685706},
{"learn":[0.1201516909],"iteration":757,"passed_time":9.247716522,"remaining_time":2.952437201},
{"learn":[0.1201075766],"iteration":758,"passed_time":9.258593617,"remaining_time":2.939816945},
{"learn":[0.119861362],"iteration":759,"passed_time":9.270398806,"remaining_time":2.92749436},
{"learn":[0.1197303469],"iteration":760,"passed_time":9.289038277,"remaining_time":2.917319511},
{"learn":[0.1195887073],"iteration":761,"passed_time":9.30742408,"remaining_time":2.907043217},
{"learn":[0.1194058069],"iteration":762,"passed_time":9.325758592,"remaining_time":2.896729733},
{"learn":[0.1192749712],"iteration":763,"passed_time":9.343771871,"remaining_time":2.886296023},
{"learn":[0.1191314176],"iteration":764,"passed_time":9.357459006,"remaining_time":2.874513551},
{"learn":[0.1189075337],"iteration":765,"passed_time":9.368692299,"remaining_time":2.861976499},
{"learn":[0.1187108732],"iteration":766,"passed_time":9.380382042,"remaining_time":2.849581507},
{"learn":[0.1186447589],"iteration":767,"passed_time":9.391261783,"remaining_time":2.836943664},
{"learn":[0.1184517278],"iteration":768,"passed_time":9.403078383,"remaining_time":2.824591816},
{"learn":[0.1183032739],"iteration":769,"passed_time":9.415912223,"remaining_time":2.812545209},
{"learn":[0.1182545875],"iteration":770,"passed_time":9.427521458,"remaining_time":2.800132833},
{"learn":[0.1182542538],"iteration":771,"passed_time":9.432092056,"remaining_time":2.785643768},
{"learn":[0.1180493346],"iteration":772,"passed_time":9.443737102,"remaining_time":2.773257855},
{"learn":[0.1180390839],"iteration":773,"passed_time":9.450572803,"remaining_time":2.759469578},
{"learn":[0.1180018948],"iteration":774,"passed_time":9.459826607,"remaining_time":2.746401273},
{"learn":[0.1179303422],"iteration":775,"passed_time":9.467758904,"remaining_time":2.732961333},
{"learn":[0.1178651382],"iteration":776,"passed_time":9.479887455,"remaining_time":2.7207399},
{"learn":[0.1177767684],"iteration":777,"passed_time":9.491873543,"remaining_time":2.708478055},
{"learn":[0.1176669348],"iteration":778,"passed_time":9.504544667,"remaining_time":2.69641126},
{"learn":[0.1174886255],"iteration":779,"passed_time":9.517625322,"remaining_time":2.684458424},
{"learn":[0.1172429694],"iteration":780,"passed_time":9.531117219,"remaining_time":2.672618017},
{"learn":[0.1170959991],"iteration":781,"passed_time":9.545434089,"remaining_time":2.661003365},
{"learn":[0.1169599566],"iteration":782,"passed_time":9.558042915,"remaining_time":2.648908445},
{"learn":[0.1169072015],"iteration":783,"passed_time":9.570194811,"remaining_time":2.636686326},
{"learn":[0.1167875594],"iteration":784,"passed_time":9.582912347,"remaining_time":2.624619305},
{"learn":[0.1166232689],"iteration":785,"passed_time":9.596273185,"remaining_time":2.612725778},
{"learn":[0.1165215724],"iteration":786,"passed_time":9.608700355,"remaining_time":2.600575827},
{"learn":[0.1163852443],"iteration":787,"passed_time":9.621442378,"remaining_time":2.588509878},
{"learn":[0.116372744],"iteration":788,"passed_time":9.630297605,"remaining_time":2.575402782},
{"learn":[0.1161742226],"iteration":789,"passed_time":9.645000423,"remaining_time":2.563860872},
{"learn":[0.1161163428],"iteration":790,"passed_time":9.657598304,"remaining_time":2.551754798},
{"learn":[0.1159895982],"iteration":791,"passed_time":9.669960262,"remaining_time":2.539585523},
{"learn":[0.1158362456],"iteration":792,"passed_time":9.683012754,"remaining_time":2.527596015},
{"learn":[0.1157315008],"iteration":793,"passed_time":9.695958389,"remaining_time":2.515576106},
{"learn":[0.1155743145],"iteration":794,"passed_time":9.709125317,"remaining_time":2.503610931},
{"learn":[0.1154825948],"iteration":795,"passed_time":9.722336632,"remaining_time":2.491654112},
{"learn":[0.1152984436],"iteration":796,"passed_time":9.735355025,"remaining_time":2.479645006},
{"learn":[0.115175517],"iteration":797,"passed_time":9.753929079,"remaining_time":2.469039692},
{"learn":[0.1150236068],"iteration":798,"passed_time":9.771781617,"remaining_time":2.458232922},
{"learn":[0.1149491475],"iteration":799,"passed_time":9.784329379,"remaining_time":2.446082345},
{"learn":[0.1148732462],"iteration":800,"passed_time":9.79681476,"remaining_time":2.433915277},
{"learn":[0.1148296185],"iteration":801,"passed_time":9.809403884,"remaining_time":2.421773029},
{"learn":[0.1146029054],"iteration":802,"passed_time":9.824312115,"remaining_time":2.410198613},
{"learn":[0.1144866797],"iteration":803,"passed_time":9.83656484,"remaining_time":2.397968543},
{"learn":[0.1143634029],"iteration":804,"passed_time":9.848025526,"remaining_time":2.385546556},
{"learn":[0.1142487908],"iteration":805,"passed_time":9.860271699,"remaining_time":2.373316017},
{"learn":[0.1142261903],"iteration":806,"passed_time":9.868622235,"remaining_time":2.360153769},
{"learn":[0.114125832],"iteration":807,"passed_time":9.880564993,"remaining_time":2.347857028},
{"learn":[0.1139329139],"iteration":808,"passed_time":9.892646075,"remaining_time":2.33559382},
{"learn":[0.1138084669],"iteration":809,"passed_time":9.904861497,"remaining_time":2.323362573},
{"learn":[0.1136542468],"iteration":810,"passed_time":9.917158595,"remaining_time":2.3111504},
{"learn":[0.1135750899],"iteration":811,"passed_time":9.931563498,"remaining_time":2.299426031},
{"learn":[0.113445474],"iteration":812,"passed_time":9.949209114,"remaining_time":2.288440473},
{"learn":[0.1132467063],"iteration":813,"passed_time":9.967832191,"remaining_time":2.277661901},
{"learn":[0.113043303],"iteration":814,"passed_time":9.98695536,"remaining_time":2.266977597},
{"learn":[0.1129407846],"iteration":815,"passed_time":10.00580559,"remaining_time":2.256211065},
{"learn":[0.1128383173],"iteration":816,"passed_time":10.01837401,"remaining_time":2.244017678},
{"learn":[0.1128150842],"iteration":817,"passed_time":10.03562299,"remaining_time":2.232864774},
{"learn":[0.1126841794],"iteration":818,"passed_time":10.04897119,"remaining_time":2.220834903},
{"learn":[0.1125812692],"iteration":819,"passed_time":10.0618209,"remaining_time":2.208692393},
{"learn":[0.1125118896],"iteration":820,"passed_time":10.07628198,"remaining_time":2.196899481},
{"learn":[0.1123336274],"iteration":821,"passed_time":10.08794445,"remaining_time":2.184494054},
{"learn":[0.1122833599],"iteration":822,"passed_time":10.09980068,"remaining_time":2.172132102},
{"learn":[0.1120028914],"iteration":823,"passed_time":10.11113945,"remaining_time":2.159660854},
{"learn":[0.1119206669],"iteration":824,"passed_time":10.12119453,"remaining_time":2.146920052},
{"learn":[0.1118691109],"iteration":825,"passed_time":10.13504537,"remaining_time":2.134985344},
{"learn":[0.1117531566],"iteration":826,"passed_time":10.14774712,"remaining_time":2.122805625},
{"learn":[0.1116623239],"iteration":827,"passed_time":10.16022867,"remaining_time":2.110578902},
{"learn":[0.1115262302],"iteration":828,"passed_time":10.17217532,"remaining_time":2.09824123},
{"learn":[0.1113501401],"iteration":829,"passed_time":10.18422568,"remaining_time":2.085925741},
{"learn":[0.1112831101],"iteration":830,"passed_time":10.19588265,"remaining_time":2.073530888},
{"learn":[0.1111157669],"iteration":831,"passed_time":10.20782876,"remaining_time":2.061196192},
{"learn":[0.111027504],"iteration":832,"passed_time":10.21995206,"remaining_time":2.048897953},
{"learn":[0.1109464138],"iteration":833,"passed_time":10.23148845,"remaining_time":2.036483312},
{"learn":[0.1108746562],"iteration":834,"passed_time":10.24428632,"remaining_time":2.024320052},
{"learn":[0.1107397129],"iteration":835,"passed_time":10.25831265,"remaining_time":2.012396262},
{"learn":[0.1105734022],"iteration":836,"passed_time":10.271887,"remaining_time":2.000379427},
{"learn":[0.1103082632],"iteration":837,"passed_time":10.28434979,"remaining_time":1.988143992},
{"learn":[0.1102276745],"iteration":838,"passed_time":10.29630731,"remaining_time":1.975811058},
{"learn":[0.1101641474],"iteration":839,"passed_time":10.30784021,"remaining_time":1.963398135},
{"learn":[0.1099996515],"iteration":840,"passed_time":10.32025293,"remaining_time":1.951153646},
{"learn":[0.1098200636],"iteration":841,"passed_time":10.33179189,"remaining_time":1.938744796},
{"learn":[0.1096691115],"iteration":842,"passed_time":10.34321288,"remaining_time":1.92631604},
{"learn":[0.1095094592],"iteration":843,"passed_time":10.35608224,"remaining_time":1.914157382},
{"learn":[0.1093581504],"iteration":844,"passed_time":10.36828783,"remaining_time":1.901875283},
{"learn":[0.1091994492],"iteration":845,"passed_time":10.37969678,"remaining_time":1.889448351},
{"learn":[0.1090416768],"iteration":846,"passed_time":10.39151062,"remaining_time":1.877096961},
{"learn":[0.1089833206],"iteration":847,"passed_time":10.40410617,"remaining_time":1.864886954},
{"learn":[0.1088777941],"iteration":848,"passed_time":10.41587957,"remaining_time":1.852529817},
{"learn":[0.1087353507],"iteration":849,"passed_time":10.42729021,"remaining_time":1.840110037},
{"learn":[0.1086087545],"iteration":850,"passed_time":10.43952445,"remaining_time":1.827836831},
{"learn":[0.1085383751],"iteration":851,"passed_time":10.45174495,"remaining_time":1.815561329},
{"learn":[0.1084157953],"iteration":852,"passed_time":10.46432988,"remaining_time":1.80334876},
{"learn":[0.1082999665],"iteration":853,"passed_time":10.47686323,"remaining_time":1.791126501},
{"learn":[0.1082174671],"iteration":854,"passed_time":10.48708428,"remaining_time":1.77851137},
{"learn":[0.1080139947],"iteration":855,"passed_time":10.49954758,"remaining_time":1.766279031},
{"learn":[0.1079356194],"iteration":856,"passed_time":10.511482,"remaining_time":1.753957906},
{"learn":[0.1078652929],"iteration":857,"passed_time":10.52480471,"remaining_time":1.741867446},
{"learn":[0.1077367308],"iteration":858,"passed_time":10.53742926,"remaining_time":1.729659518},
{"learn":[0.1075616381],"iteration":859,"passed_time":10.54952106,"remaining_time":1.717363893},
{"learn":[0.1074541862],"iteration":860,"passed_time":10.56176292,"remaining_time":1.705092969},
{"learn":[0.107310851],"iteration":861,"passed_time":10.57675614,"remaining_time":1.693262583},
{"learn":[0.1072492239],"iteration":862,"passed_time":10.59027773,"remaining_time":1.68119125},
{"learn":[0.1071586339],"iteration":863,"passed_time":10.60872264,"remaining_time":1.669891526},
{"learn":[0.1070543355],"iteration":864,"passed_time":10.62600068,"remaining_time":1.65839317},
{"learn":[0.1068881562],"iteration":865,"passed_time":10.64222226,"remaining_time":1.646717994},
{"learn":[0.106807944],"iteration":866,"passed_time":10.65766567,"remaining_time":1.634912958},
{"learn":[0.1067182566],"iteration":867,"passed_time":10.66716425,"remaining_time":1.622195485},
{"learn":[0.1066671757],"iteration":868,"passed_time":10.67908136,"remaining_time":1.609850009},
{"learn":[0.1065664755],"iteration":869,"passed_time":10.69106738,"remaining_time":1.597515815},
{"learn":[0.1065087423],"iteration":870,"passed_time":10.70520084,"remaining_time":1.585500469},
{"learn":[0.1064284218],"iteration":871,"passed_time":10.71762429,"remaining_time":1.573229254},
{"learn":[0.1063528407],"iteration":872,"passed_time":10.72942782,"remaining_time":1.560867507},
{"learn":[0.1061818864],"iteration":873,"passed_time":10.74169098,"remaining_time":1.548573299},
{"learn":[0.1059653046],"iteration":874,"passed_time":10.75422188,"remaining_time":1.536317411},
{"learn":[0.1058205776],"iteration":875,"passed_time":10.76648002,"remaining_time":1.524022287},
{"learn":[0.1056891689],"iteration":876,"passed_time":10.77975769,"remaining_time":1.511870235},
{"learn":[0.1056350928],"iteration":877,"passed_time":10.79253583,"remaining_time":1.499646209},
{"learn":[0.1054673109],"iteration":878,"passed_time":10.80548229,"remaining_time":1.487444093},
{"learn":[0.1053691728],"iteration":879,"passed_time":10.81820074,"remaining_time":1.475209192},
{"learn":[0.1052447142],"iteration":880,"passed_time":10.83001604,"remaining_time":1.462851202},
{"learn":[0.1050644813],"iteration":881,"passed_time":10.84184048,"remaining_time":1.450495665},
{"learn":[0.1048855075],"iteration":882,"passed_time":10.85663871,"remaining_time":1.438535367},
{"learn":[0.1048091598],"iteration":883,"passed_time":10.86898484,"remaining_time":1.426246879},
{"learn":[0.1047552028],"iteration":884,"passed_time":10.88283126,"remaining_time":1.414153214},
{"learn":[0.1046554717],"iteration":885,"passed_time":10.89496739,"remaining_time":1.401835533},
{"learn":[0.1045219276],"iteration":886,"passed_time":10.90641785,"remaining_time":1.38943091},
{"learn":[0.1044583414],"iteration":887,"passed_time":10.91901173,"remaining_time":1.37717265},
{"learn":[0.1043747242],"iteration":888,"passed_time":10.93093816,"remaining_time":1.364830299},
{"learn":[0.1042101384],"iteration":889,"passed_time":10.94291986,"remaining_time":1.352495713},
{"learn":[0.1041240212],"iteration":890,"passed_time":10.95429009,"remaining_time":1.340087115},
{"learn":[0.1039278728],"iteration":891,"passed_time":10.96627175,"remaining_time":1.327754875},
{"learn":[0.1038453239],"iteration":892,"passed_time":10.97856571,"remaining_time":1.315460841},
{"learn":[0.1037128846],"iteration":893,"passed_time":10.98958087,"remaining_time":1.303015181},
{"learn":[0.1035487462],"iteration":894,"passed_time":11.00273276,"remaining_time":1.290823397},
{"learn":[0.1035007566],"iteration":895,"passed_time":11.01534953,"remaining_time":1.278567356},
{"learn":[0.1034450108],"iteration":896,"passed_time":11.02715765,"remaining_time":1.266217657},
{"learn":[0.1033571619],"iteration":897,"passed_time":11.03891971,"remaining_time":1.253863931},
{"learn":[0.1031928638],"iteration":898,"passed_time":11.05245174,"remaining_time":1.241710373},
{"learn":[0.1029871458],"iteration":899,"passed_time":11.06645502,"remaining_time":1.229606113},
{"learn":[0.1029361145],"iteration":900,"passed_time":11.07865942,"remaining_time":1.21729998},
{"learn":[0.1027914608],"iteration":901,"passed_time":11.09027321,"remaining_time":1.204929905},
{"learn":[0.1026290634],"iteration":902,"passed_time":11.10319716,"remaining_time":1.192702242},
{"learn":[0.1025087308],"iteration":903,"passed_time":11.11780106,"remaining_time":1.18065144},
{"learn":[0.1023403627],"iteration":904,"passed_time":11.12983575,"remaining_time":1.1683253},
{"learn":[0.1022024063],"iteration":905,"passed_time":11.14134858,"remaining_time":1.155945658},
{"learn":[0.1021002087],"iteration":906,"passed_time":11.15321192,"remaining_time":1.143603868},
{"learn":[0.102038922],"iteration":907,"passed_time":11.16546619,"remaining_time":1.131302742},
{"learn":[0.1018744421],"iteration":908,"passed_time":11.17900832,"remaining_time":1.119130646},
{"learn":[0.1017449219],"iteration":909,"passed_time":11.19127841,"remaining_time":1.106829732},
{"learn":[0.1016167886],"iteration":910,"passed_time":11.20369766,"remaining_time":1.094543459},
{"learn":[0.1014348821],"iteration":911,"passed_time":11.21605696,"remaining_time":1.08225111},
{"learn":[0.1013633688],"iteration":912,"passed_time":11.22699326,"remaining_time":1.069823016},
{"learn":[0.1012824979],"iteration":913,"passed_time":11.23823247,"remaining_time":1.057426688},
{"learn":[0.1011083011],"iteration":914,"passed_time":11.25035556,"remaining_time":1.045114997},
{"learn":[0.1009759571],"iteration":915,"passed_time":11.26214515,"remaining_time":1.032773136},
{"learn":[0.1008508835],"iteration":916,"passed_time":11.27375656,"remaining_time":1.020416351},
{"learn":[0.1007481317],"iteration":917,"passed_time":11.28580297,"remaining_time":1.008100047},
{"learn":[0.1006456907],"iteration":918,"passed_time":11.29821452,"remaining_time":0.9958165139},
{"learn":[0.1005326301],"iteration":919,"passed_time":11.31155487,"remaining_time":0.983613467},
{"learn":[0.1004062638],"iteration":920,"passed_time":11.32379679,"remaining_time":0.9713137311},
{"learn":[0.1002965062],"iteration":921,"passed_time":11.3363203,"remaining_time":0.959037943},
{"learn":[0.1002032922],"iteration":922,"passed_time":11.34736408,"remaining_time":0.9466381734},
{"learn":[0.1000283315],"iteration":923,"passed_time":11.3594164,"remaining_time":0.9343242929},
{"learn":[0.09987428222],"iteration":924,"passed_time":11.37076234,"remaining_time":0.921953703},
{"learn":[0.09975400514],"iteration":925,"passed_time":11.38263119,"remaining_time":0.9096271148},
{"learn":[0.09959511749],"iteration":926,"passed_time":11.39457414,"remaining_time":0.897307349},
{"learn":[0.09945085894],"iteration":927,"passed_time":11.4070151,"remaining_time":0.8850270335},
{"learn":[0.09929000197],"iteration":928,"passed_time":11.41955185,"remaining_time":0.8727536937},
{"learn":[0.09925798731],"iteration":929,"passed_time":11.43139739,"remaining_time":0.8604277608},
{"learn":[0.09920322614],"iteration":930,"passed_time":11.44317755,"remaining_time":0.8480980138},
{"learn":[0.09911218954],"iteration":931,"passed_time":11.45443494,"remaining_time":0.8357313044},
{"learn":[0.09896441314],"iteration":932,"passed_time":11.46665275,"remaining_time":0.8234359421},
{"learn":[0.09881413464],"iteration":933,"passed_time":11.4783532,"remaining_time":0.8111041878},
{"learn":[0.0987436281],"iteration":934,"passed_time":11.49045196,"remaining_time":0.7988014734},
{"learn":[0.09867648244],"iteration":935,"passed_time":11.50189896,"remaining_time":0.7864546296},
{"learn":[0.0985458743],"iteration":936,"passed_time":11.51512504,"remaining_time":0.7742293252},
{"learn":[0.09837669169],"iteration":937,"passed_time":11.52695021,"remaining_time":0.7619092892},
{"learn":[0.09827081192],"iteration":938,"passed_time":11.53960569,"remaining_time":0.7496442459},
{"learn":[0.09820717086],"iteration":939,"passed_time":11.55111043,"remaining_time":0.7373049211},
{"learn":[0.09808801713],"iteration":940,"passed_time":11.56353519,"remaining_time":0.7250250541},
{"learn":[0.09797495855],"iteration":941,"passed_time":11.57553237,"remaining_time":0.7127185537},
{"learn":[0.09786989087],"iteration":942,"passed_time":11.5879188,"remaining_time":0.700436237},
{"learn":[0.09781854579],"iteration":943,"passed_time":11.59985407,"remaining_time":0.6881269361},
{"learn":[0.09767876701],"iteration":944,"passed_time":11.61366433,"remaining_time":0.6759275536},
{"learn":[0.09755542169],"iteration":945,"passed_time":11.62540687,"remaining_time":0.6636067348},
{"learn":[0.09746785106],"iteration":946,"passed_time":11.63737677,"remaining_time":0.6512998614},
{"learn":[0.09737298136],"iteration":947,"passed_time":11.64999751,"remaining_time":0.6390293993},
{"learn":[0.09732169259],"iteration":948,"passed_time":11.66203017,"remaining_time":0.6267265949},
{"learn":[0.09724682113],"iteration":949,"passed_time":11.68163345,"remaining_time":0.6148228132},
{"learn":[0.09716766557],"iteration":950,"passed_time":11.69401503,"remaining_time":0.6025307428},
{"learn":[0.09702901482],"iteration":951,"passed_time":11.70671295,"remaining_time":0.5902544347},
{"learn":[0.09697280235],"iteration":952,"passed_time":11.71865581,"remaining_time":0.5779400035},
{"learn":[0.09692534823],"iteration":953,"passed_time":11.73300501,"remaining_time":0.5657423801},
{"learn":[0.09684373603],"iteration":954,"passed_time":11.74661196,"remaining_time":0.5535052755},
{"learn":[0.09673261686],"iteration":955,"passed_time":11.75955192,"remaining_time":0.541234607},
{"learn":[0.09667946642],"iteration":956,"passed_time":11.77163213,"remaining_time":0.5289239099},
{"learn":[0.09654356004],"iteration":957,"passed_time":11.78360612,"remaining_time":0.5166090367},
{"learn":[0.09645447938],"iteration":958,"passed_time":11.79657252,"remaining_time":0.5043373027},
{"learn":[0.09642150352],"iteration":959,"passed_time":11.80655789,"remaining_time":0.491939912},
{"learn":[0.09635975166],"iteration":960,"passed_time":11.81824962,"remaining_time":0.4796167902},
{"learn":[0.09622565393],"iteration":961,"passed_time":11.83165626,"remaining_time":0.4673627213},
{"learn":[0.09612211236],"iteration":962,"passed_time":11.84409297,"remaining_time":0.4550689926},
{"learn":[0.09600824729],"iteration":963,"passed_time":11.85621709,"remaining_time":0.4427632937},
{"learn":[0.09586681334],"iteration":964,"passed_time":11.86825874,"remaining_time":0.4304549801},
{"learn":[0.09573902599],"iteration":965,"passed_time":11.8804793,"remaining_time":0.4181535157},
{"learn":[0.09563329247],"iteration":966,"passed_time":11.89322956,"remaining_time":0.4058702952},
{"learn":[0.09548003681],"iteration":967,"passed_time":11.91938233,"remaining_time":0.3940291678},
{"learn":[0.09541397017],"iteration":968,"passed_time":11.93229056,"remaining_time":0.3817347857},
{"learn":[0.09536615573],"iteration":969,"passed_time":11.94480943,"remaining_time":0.3694270957},
{"learn":[0.09527438065],"iteration":970,"passed_time":11.95688249,"remaining_time":0.3571056563},
{"learn":[0.09518283994],"iteration":971,"passed_time":11.9692758,"remaining_time":0.3447939532},
{"learn":[0.0950796818],"iteration":972,"passed_time":11.98133092,"remaining_time":0.3324726977},
{"learn":[0.09502639909],"iteration":973,"passed_time":11.99376194,"remaining_time":0.3201620231},
{"learn":[0.09502000163],"iteration":974,"passed_time":11.99883681,"remaining_time":0.3076624822},
{"learn":[0.09487006226],"iteration":975,"passed_time":12.01232516,"remaining_time":0.295385045},
{"learn":[0.0947329945],"iteration":976,"passed_time":12.02596155,"remaining_time":0.2831086137},
{"learn":[0.09465330573],"iteration":977,"passed_time":12.03844089,"remaining_time":0.2708033739},
{"learn":[0.09446977762],"iteration":978,"passed_time":12.04991754,"remaining_time":0.2584762701},
{"learn":[0.09438852314],"iteration":979,"passed_time":12.06215409,"remaining_time":0.2461664099},
{"learn":[0.09428516981],"iteration":980,"passed_time":12.07430062,"remaining_time":0.233854956},
{"learn":[0.09423613961],"iteration":981,"passed_time":12.08693609,"remaining_time":0.2215528},
{"learn":[0.0940859589],"iteration":982,"passed_time":12.09841932,"remaining_time":0.2092300391},
{"learn":[0.09398709989],"iteration":983,"passed_time":12.11139396,"remaining_time":0.1969332352},
{"learn":[0.09385846938],"iteration":984,"passed_time":12.12320173,"remaining_time":0.1846172852},
{"learn":[0.09370447183],"iteration":985,"passed_time":12.1361735,"remaining_time":0.1723188935},
{"learn":[0.09368327451],"iteration":986,"passed_time":12.14814767,"remaining_time":0.1600059976},
{"learn":[0.09359535644],"iteration":987,"passed_time":12.16152726,"remaining_time":0.1477108574},
{"learn":[0.09348539739],"iteration":988,"passed_time":12.17424826,"remaining_time":0.135406199},
{"learn":[0.0934147149],"iteration":989,"passed_time":12.18715745,"remaining_time":0.1231026005},
{"learn":[0.09337253731],"iteration":990,"passed_time":12.19869796,"remaining_time":0.1107853498},
{"learn":[0.09320351333],"iteration":991,"passed_time":12.21079358,"remaining_time":0.09847414175},
{"learn":[0.09314391257],"iteration":992,"passed_time":12.22289816,"remaining_time":0.08616343117},
{"learn":[0.09309483604],"iteration":993,"passed_time":12.2366286,"remaining_time":0.07386294928},
{"learn":[0.09294856497],"iteration":994,"passed_time":12.24878673,"remaining_time":0.06155169212},
{"learn":[0.09284724238],"iteration":995,"passed_time":12.26066896,"remaining_time":0.04923963438},
{"learn":[0.09283871838],"iteration":996,"passed_time":12.26777404,"remaining_time":0.03691406432},
{"learn":[0.09276833492],"iteration":997,"passed_time":12.27913894,"remaining_time":0.02460749286},
{"learn":[0.09263212896],"iteration":998,"passed_time":12.29137172,"remaining_time":0.0123036754},
{"learn":[0.09250074612],"iteration":999,"passed_time":12.30433374,"remaining_time":0}
]}